Workbook

Sheet Title
B2: M-TERMINAL
B4: Institutional Equity Research · Modeling Lab
B5: =Assumptions!E9 -> DCF Valuation Model
B7: Worksheets
B8: =HYPERLINK("#"&CELL("address",Terms!$F$21),"Terms and Abbreviationss") -> Terms and Abbreviationss
B9: =HYPERLINK("#"&CELL("address",'Executive Summary'!$F$10),"Executive Summary") -> Executive Summary
B10: =HYPERLINK("#"&CELL("address",Assumptions!$G$14),"Assumptions") -> Assumptions
B11: =HYPERLINK("#"&CELL("address",Financials!$K$31),"Financials") -> Financials
B12: =HYPERLINK("#"&CELL("address",DCF!$M$51),"DCF") -> DCF
B13: =HYPERLINK("#"&CELL("address",'Terminal Value'!$H$138),"Terminal Value") -> Terminal Value
B14: =HYPERLINK("#"&CELL("address",'Two Stage Value Driver Model'!$R$47),"Two Stage Value Driver Model") -> Two Stage Value Driver Model

Sheet Terms
B2: =Title!$B$5 -> DCF Valuation Model
C5: Instructions
C7: Cell Colors
C9: How to Work with this Model
C11: Assumption | F11: Cells which contain the assumptions. Are not linked to any other cells.
C12: Linked Assumption | F12: Cells which also contain assumptions but are linked to other assumption. Can either be left "as is" or overwritten if needed.
C13: Link and calculations | F13: Cells which contain links or calculations. Should not be changed unless you want to change the logic of the model
C14: Linked to cells in other sheets | F14: Cells which contains links from cells from other sheets
C17: Terms & Abbreviations
C19: Terms & Abbreviations
C21: CAPEX | E21: Capital Expenditures
C22: DCF | E22: Discounted Cash Flow
C23: EBIT | E23: Earnings before Interest and Tax
C24: EBITDA | E24: Earnings before Interest, Tax, Depreciation and Amoritization
C25: EBT | E25: Earnings before Tax
C26: EPS | E26: Earnings Per Share
C27: EV | E27: Enterprise Value
C28: EV/EBITDA | E28: Enterprise Value/EBIT
C29: EV/EBITDA | E29: Enterprise Value/EBITDA
C30: EV/Revenue | E30: Enterprise Value/Revenue
C31: FCF | E31: Free Cash Flow
C32: g | E32: Growth Rate
... C36: NOPLAT | E36: Net Operating Profit less Adjusted Taxes
F37: > NOPLAT = =EBIT × (1 - Tax Rate)
F38: > NOPLAT shows how much profit a company makes from its operations after paying taxes, but before financing costs (like interest).
F39: > It focuses only on the core business performance, ignoring debt/equity structure.
C40: OPEX | E40: Operating Expenses
C41: PV | E41: Present Value
C42: P/B | E42: Price per Book
C43: P/E | E43: Price to Earnings
C44: PV | E44: Present Value
C45: ROA | E45: Return on assets
F46: > Adjusted ROA measures how efficiently a company uses its total assets to generate operating profit before taxes.
F47: > By removing the impact of income taxes, this metric provides a clearer view of core asset performance,
F48: and is especially useful for cross-company or cross-border comparisons.
C49: ROCE | E49: Return on capital employed
F50: = EBIT / Capital Employed
F51: > ROCE measures how efficiently a company uses all its capital to generate profit.
F52: > It's useful for comparing profitability across companies regardless of debt/equity levels.
C53: ROIC | E53: Return on invested capital
F54: = NOPAT / Invested Capital
F55: > ROIC shows how well a company turns capital (from both debt and equity) into profit.
F56: > It's similar to ROCE, but focuses more on core operating assets.
C57: TV | E57: Terminal Value
C58: t | E58: Tax Rate
C59: Unlev. FCFF | E59: Unlevered Free Cash Flow to Firm
C60: USD | E60: United States Dollar
C61: WACC | E61: Weighted Average Cost of Capital
C62: Y | E62: Year

Sheet Executive Summary
B2: =Title!$B$5 -> DCF Valuation Model | W2: =Title!#REF!&" "&Title!#REF! -> #REF! | Y2: Checks
W3: =Title!#REF! -> #REF! | Y3: =SUM(Y5:Z141) -> 0
C5: Financial Summary
C6: ="All amounts in "&Assumptions!$G$14 -> All amounts in USD
A7: 1 | C7: =Financials!C7 -> Income Statement | E7: =Financials!G7 -> Unit | F7: =Financials!M7 -> 2026 | G7: =Financials!O7 -> 2027 | H7: =Financials!P7 -> 2028 | I7: =Financials!Q7 -> 2029 | J7: =Financials!R7 -> 2030 | K7: =Financials!S7 -> 2031 | N7: =Financials!C38 -> Balance Sheet | P7: =E7 -> Unit | Q7: =F7 -> 2026 | R7: =G7 -> 2027 | S7: =H7 -> 2028 | T7: =I7 -> 2029 | U7: =J7 -> 2030 | V7: =K7 -> 2031
C8: =Financials!C8 -> Forecast Year | F8: =Financials!M8 -> 0 | G8: =Financials!O8 -> 1 | H8: =Financials!P8 -> 2 | I8: =Financials!Q8 -> 3 | J8: =Financials!R8 -> 4 | K8: =Financials!S8 -> 5 | N8: =C8 -> Forecast Year | Q8: =F8 -> 0 | R8: =G8 -> 1 | S8: =H8 -> 2 | T8: =I8 -> 3 | U8: =J8 -> 4 | V8: =K8 -> 5
C10: =Financials!C10 -> Revenue | E10: =Financials!G10 -> USD | F10: =Financials!N10 -> 5263000 | G10: =Financials!O10 -> 5657725 | H10: =Financials!P10 -> 6082054.4 | I10: =Financials!Q10 -> 6386157.1 | J10: =Financials!R10 -> 6705464.9 | K10: =Financials!S10 -> 7040738.2 | N10: =Financials!C41 -> Cash | P10: =Financials!G41 -> USD | Q10: =Financials!N41 -> 600000 | R10: =Financials!O41 -> 971699.34 | S10: =Financials!P41 -> 1383738.1 | T10: =Financials!Q41 -> 1846341.9 | U10: =Financials!R41 -> 2063345 | V10: =Financials!S41 -> 2543752.2
C11: =Financials!C11 -> Revenue Growth | E11: =Financials!G11 -> % | F11: =Financials!N11 -> 0.0526 | G11: =Financials!O11 -> 0.075 | H11: =Financials!P11 -> 0.075 | I11: =Financials!Q11 -> 0.05 | J11: =Financials!R11 -> 0.05 | K11: =Financials!S11 -> 0.05 | N11: =Financials!C42 -> Receivables | P11: =Financials!G42 -> USD | Q11: =Financials!N42 -> 432575.34 | R11: =Financials!O42 -> 465018.49 | S11: =Financials!P42 -> 498529.05 | T11: =Financials!Q42 -> 524889.62 | U11: =Financials!R42 -> 551134.11 | V11: =Financials!S42 -> 578690.81
N12: =Financials!C43 -> Inventory | P12: =Financials!G43 -> USD | Q12: =Financials!N43 -> 108143.84 | R12: =Financials!O43 -> 130205.18 | S12: =Financials!P43 -> 139588.13 | T12: =Financials!Q43 -> 144344.65 | U12: =Financials!R43 -> 151561.88 | V12: =Financials!S43 -> 159139.97
C13: =Financials!C13 -> Direct Costs | E13: =Financials!G13 -> USD | F13: =Financials!N13 -> -2631500 | G13: =Financials!O13 -> -3168326 | H13: =Financials!P13 -> -3405950.5 | I13: =Financials!Q13 -> -3512386.4 | J13: =Financials!R13 -> -3688005.7 | K13: =Financials!S13 -> -3872406 | N13: =Financials!C44 -> Other Current Assets | P13: =Financials!G44 -> USD | Q13: =Financials!N44 -> 26315 | R13: =Financials!O44 -> 28288.625 | S13: =Financials!P44 -> 30410.272 | T13: =Financials!Q44 -> 31930.785 | U13: =Financials!R44 -> 33527.325 | V13: =Financials!S44 -> 35203.691
C14: =Financials!C14 -> Gross Profit | E14: =Financials!G14 -> USD | F14: =F10+F13 -> 2631500 | G14: =G10+G13 -> 2489399 | H14: =H10+H13 -> 2676103.9 | I14: =I10+I13 -> 2873770.7 | J14: =J10+J13 -> 3017459.2 | K14: =K10+K13 -> 3168332.2 | N14: =Financials!C45 -> Current Assets | P14: =Financials!G45 -> USD | Q14: =SUM(Q10:Q13) -> 1167034.2 | R14: =Financials!O45 -> 1595211.6 | S14: =Financials!P45 -> 2052265.5 | T14: =Financials!Q45 -> 2547507 | U14: =Financials!R45 -> 2799568.3 | V14: =Financials!S45 -> 3316786.7
C15: =Financials!C15 -> Gross Profit Margin % | E15: =Financials!G15 -> % of Revenue | F15: =Financials!N15 -> 0.5 | G15: =Financials!O15 -> 0.44 | H15: =Financials!P15 -> 0.44 | I15: =Financials!Q15 -> 0.45 | J15: =Financials!R15 -> 0.45 | K15: =Financials!S15 -> 0.45
N16: =Financials!C47 -> Capital Expenditures | P16: =P17 -> USD | Q16: =Financials!N47 -> 1500000 | R16: =Financials!O47 -> 1200000 | S16: =Financials!P47 -> 900000 | T16: =Financials!Q47 -> 600000 | U16: =Financials!R47 -> 550000 | V16: =Financials!S47 -> 200000
C17: =Financials!C17 -> Operating Expenses | E17: =Financials!G17 -> USD | F17: =Financials!N17 -> -1350000 | G17: =Financials!O17 -> -1388714.3 | H17: =Financials!P17 -> -1492867.9 | I17: =Financials!Q17 -> -1612297.3 | J17: =Financials!R17 -> -1757404.1 | K17: =Financials!S17 -> -1933144.5 | N17: =Financials!C48 -> Fixed Assets | P17: =Financials!G47 -> USD | Q17: =SUM(Q16) -> 1500000 | R17: =SUM(R16) -> 1200000 | S17: =SUM(S16) -> 900000 | T17: =SUM(T16) -> 600000 | U17: =SUM(U16) -> 550000 | V17: =SUM(V16) -> 200000
C18: =Financials!C18 -> EBITDA | E18: =Financials!G18 -> USD | F18: =F14+F17 -> 1281500 | G18: =G14+G17 -> 1100684.7 | H18: =H14+H17 -> 1183236 | I18: =I14+I17 -> 1261473.4 | J18: =J14+J17 -> 1260055.1 | K18: =K14+K17 -> 1235187.7
C19: =Financials!C19 -> EBITDA Margin % | E19: =Financials!G19 -> % of Revenue | F19: =Financials!N19 -> 0.2434923 | G19: =Financials!O19 -> 0.19454545 | H19: =Financials!P19 -> 0.19454545 | I19: =Financials!Q19 -> 0.19753247 | J19: =Financials!R19 -> 0.18791466 | K19: =Financials!S19 -> 0.1754344 | N19: =Financials!C50 -> Assets | P19: =Financials!G50 -> USD | Q19: =SUM(Q17,Q14) -> 2667034.2 | R19: =SUM(R17,R14) -> 2795211.6 | S19: =SUM(S17,S14) -> 2952265.5 | T19: =SUM(T17,T14) -> 3147507 | U19: =SUM(U17,U14) -> 3349568.3 | V19: =SUM(V17,V14) -> 3516786.7
C21: =Financials!C21 -> Depreciation | E21: =Financials!G21 -> USD | F21: =Financials!N21 -> 0 | G21: =Financials!O21 -> -300000 | H21: =Financials!P21 -> -300000 | I21: =Financials!Q21 -> -300000 | J21: =Financials!R21 -> -300000 | K21: =Financials!S21 -> -350000 | N21: =Financials!C53 -> Short-Term Provisions | P21: =Financials!G53 -> USD | Q21: =Financials!N53 -> 0 | R21: =Financials!O53 -> 0 | S21: =Financials!P53 -> 0 | T21: =Financials!Q53 -> 0 | U21: =Financials!R53 -> 0 | V21: =Financials!S53 -> 0
C22: =Financials!C25 -> Extraordinary Expenses | E22: =Financials!G25 -> USD | F22: =Financials!N25 -> 0 | G22: =Financials!O25 -> 0 | H22: =Financials!P25 -> 0 | I22: =Financials!Q25 -> 0 | J22: =Financials!R25 -> 0 | K22: =Financials!S25 -> 0 | N22: =Financials!C54 -> Payables | P22: =Financials!G54 -> USD | Q22: =Financials!N54 -> 144191.78 | R22: =Financials!O54 -> 173606.9 | S22: =Financials!P54 -> 186117.51 | T22: =Financials!Q54 -> 192459.53 | U22: =Financials!R54 -> 202082.51 | V22: =Financials!S54 -> 212186.63
C23: =Financials!C22 -> EBIT | E23: =Financials!G22 -> USD | F23: =F18+F21+F22 -> 1281500 | G23: =G18+G21+G22 -> 800684.68 | H23: =H18+H21+H22 -> 883236.03 | I23: =I18+I21+I22 -> 961473.37 | J23: =J18+J21+J22 -> 960055.14 | K23: =K18+K21+K22 -> 885187.7 | N23: =Financials!C55 -> Other Current Liabilities | P23: =Financials!G55 -> USD | Q23: =Financials!N55 -> 13157.5 | R23: =Financials!O55 -> 15841.63 | S23: =Financials!P55 -> 17029.752 | T23: =Financials!Q55 -> 17561.932 | U23: =Financials!R55 -> 18440.029 | V23: =Financials!S55 -> 19362.03
C24: =Financials!C23 -> EBIT Margin % | E24: =Financials!G23 -> % of Revenue | F24: =Financials!N23 -> 0.2434923 | G24: =Financials!O23 -> 0.14152061 | H24: =Financials!P23 -> 0.14522002 | I24: =Financials!Q23 -> 0.15055586 | J24: =Financials!R23 -> 0.14317503 | K24: =Financials!S23 -> 0.12572371 | N24: =Financials!C56 -> Short-term Liabilities | P24: =Financials!G56 -> USD | Q24: =SUM(Q21:Q23) -> 157349.28 | R24: =SUM(R21:R23) -> 189448.53 | S24: =SUM(S21:S23) -> 203147.26 | T24: =SUM(T21:T23) -> 210021.46 | U24: =SUM(U21:U23) -> 220522.53 | V24: =SUM(V21:V23) -> 231548.66
C26: =Financials!C26 -> Interest Expense | E26: =Financials!G26 -> USD | F26: =Financials!N26 -> -50000 | G26: =Financials!O26 -> -46250 | H26: =Financials!P26 -> -38750 | I26: =Financials!Q26 -> -31250 | J26: =Financials!R26 -> -23750 | K26: =Financials!S26 -> -16250 | N26: =Financials!C58 -> Long-Term Provisions | P26: =Financials!G58 -> USD | Q26: =Financials!N58 -> 0 | R26: =Financials!O58 -> 0 | S26: =Financials!P58 -> 0 | T26: =Financials!Q58 -> 0 | U26: =Financials!R58 -> 0 | V26: =Financials!S58 -> 0
C27: =Financials!C30 -> Income Taxes | E27: =Financials!G30 -> USD | F27: =Financials!N30 -> -307875 | G27: =Financials!O30 -> -188608.67 | H27: =Financials!P30 -> -211121.51 | I27: =Financials!Q30 -> -232555.84 | J27: =Financials!R30 -> -234076.29 | K27: =Financials!S30 -> -217234.42 | N27: =Financials!C59 -> Financial Debt | P27: =Financials!G59 -> USD | Q27: =Financials!N59 -> 2000000 | R27: =Financials!O59 -> 1700000 | S27: =Financials!P59 -> 1400000 | T27: =Financials!Q59 -> 1100000 | U27: =Financials!R59 -> 800000 | V27: =Financials!S59 -> 500000
C28: =Financials!C31 -> Net Income/Loss | E28: =Financials!G31 -> USD | F28: =F23+F26+F27 -> 923625 | G28: =G23+G26+G27 -> 565826.01 | H28: =H23+H26+H27 -> 633364.52 | I28: =I23+I26+I27 -> 697667.53 | J28: =J23+J26+J27 -> 702228.86 | K28: =K23+K26+K27 -> 651703.27 | N28: =Financials!C60 -> Long-term Liabilities | P28: =Financials!G60 -> USD | Q28: =SUM(Q26:Q27) -> 2000000 | R28: =SUM(R26:R27) -> 1700000 | S28: =SUM(S26:S27) -> 1400000 | T28: =SUM(T26:T27) -> 1100000 | U28: =SUM(U26:U27) -> 800000 | V28: =SUM(V26:V27) -> 500000
C29: =Financials!C32 -> Net Income/Loss Margin % | E29: =Financials!G32 -> % of Revenue | F29: =Financials!N32 -> 0.17549401 | G29: =Financials!O32 -> 0.10000946 | H29: =Financials!P32 -> 0.10413661 | I29: =Financials!Q32 -> 0.10924685 | J29: =Financials!R32 -> 0.10472486 | K29: =Financials!S32 -> 0.092561782
N30: =Financials!C62 -> Shareholder's Equity | P30: =Financials!G62 -> USD | Q30: =Financials!N62 -> 509684.9 | R30: =Financials!O62 -> 905763.11 | S30: =Financials!P62 -> 1349118.3 | T30: =Financials!Q62 -> 1837485.5 | U30: =Financials!R62 -> 2329045.7 | V30: =Financials!S62 -> 2785238
C31: Profitability & Efficiency
C32: =Financials!C133 -> Revenue/Invested Capital | E32: =Financials!G133 -> x | F32: =Financials!N133 -> 2.1337395 | G32: =Financials!O133 -> 2.7097471 | H32: =Financials!P133 -> 4.0554546 | I32: =Financials!Q133 -> 5.1993448 | J32: =Financials!R133 -> 6.2178477 | K32: =Financials!S133 -> 7.7919328 | N32: =Financials!C64 -> Liabilities & Shareholder's Equity | P32: =Financials!G64 -> USD | Q32: =SUM(Q30,Q28,Q24) -> 2667034.2 | R32: =SUM(R30,R28,R24) -> 2795211.6 | S32: =SUM(S30,S28,S24) -> 2952265.5 | T32: =SUM(T30,T28,T24) -> 3147507 | U32: =SUM(U30,U28,U24) -> 3349568.3 | V32: =SUM(V30,V28,V24) -> 3516786.7
C33: =Financials!C134 -> ROIC | E33: =Financials!G134 -> % | F33: =Financials!N134 -> 0 | G33: =Financials!O134 -> 0.2876138 | H33: =Financials!P134 -> 0.44169989 | I33: =Financials!Q134 -> 0.58709387 | J33: =Financials!R134 -> 0.6676804 | K33: =Financials!S134 -> 0.734723
C34: =Financials!C135 -> ROA | E34: =Financials!G135 -> % | F34: =Financials!N135 -> 0.29423441 | G34: =Financials!O135 -> 0.20107081 | H34: =Financials!P135 -> 0.23388158 | I34: =Financials!Q135 -> 0.23899826 | J34: =Financials!R135 -> 0.22347867 | K34: =Financials!S135 -> 0.19455833 | N34: Financial Ratios
C35: =Financials!C136 -> ROE | E35: =Financials!G136 -> % | F35: =Financials!N136 -> 0.81503877 | G35: =Financials!O136 -> 0.62054846 | H35: =Financials!P136 -> 0.56177192 | I35: =Financials!Q136 -> 0.43787529 | J35: =Financials!R136 -> 0.3370808 | K35: =Financials!S136 -> 0.25485613 | N35: =Financials!C117 -> Liquidity Ratios
N36: =Financials!C118 -> Cash Ratio | P36: =Financials!G118 -> x | Q36: =Financials!N118 -> 3.8131728 | R36: =Financials!O118 -> 5.129094 | S36: =Financials!P118 -> 6.8115025 | T36: =Financials!Q118 -> 8.7912061 | U36: =Financials!R118 -> 9.3566173 | V36: =Financials!S118 -> 10.985821
N37: =Financials!C119 -> Quick Ratio | P37: =Financials!G119 -> x | Q37: =Financials!N119 -> 6.5623137 | R37: =Financials!O119 -> 7.5836841 | S37: =Financials!P119 -> 9.2655303 | T37: =Financials!Q119 -> 11.290425 | U37: =Financials!R119 -> 11.855836 | V37: =Financials!S119 -> 13.48504
N38: =Financials!C120 -> Current Ratio | P38: =Financials!G120 -> x | Q38: =Financials!N120 -> 7.4168383 | R38: =Financials!O120 -> 8.4202902 | S38: =Financials!P120 -> 10.102354 | T38: =Financials!Q120 -> 12.129746 | U38: =Financials!R120 -> 12.695157 | V38: =Financials!S120 -> 14.324361
C39: =Financials!C71 -> Cash Flow Statement | E39: =P7 -> Unit | F39: =Q7 -> 2026 | G39: =R7 -> 2027 | H39: =S7 -> 2028 | I39: =T7 -> 2029 | J39: =U7 -> 2030 | K39: =V7 -> 2031
C40: =N8 -> Forecast Year | F40: =Q8 -> 0 | G40: =R8 -> 1 | H40: =S8 -> 2 | I40: =T8 -> 3 | J40: =U8 -> 4 | K40: =V8 -> 5 | N40: =Financials!C109 -> Bank Ratios
N41: =Financials!C110 -> Financial Debt/EBITDA | P41: =Financials!G110 -> x | Q41: =Financials!N110 -> 1.5606711 | R41: =Financials!O110 -> 1.5444932 | S41: =Financials!P110 -> 1.1831959 | T41: =Financials!Q110 -> 0.87199621 | U41: =Financials!R110 -> 0.63489285 | V41: =Financials!S110 -> 0.40479678
C42: =Financials!C83 -> Cash Flow from Operations | E42: =Financials!G83 -> USD | F42: =Financials!N83 -> 1648008.5 | G42: =Financials!O83 -> 841447.15 | H42: =Financials!P83 -> 902048.1 | I42: =Financials!Q83 -> 971904.12 | J42: =Financials!R83 -> 977671.68 | K42: =Financials!S83 -> 975918.23 | N42: =Financials!C113 -> Equity % | P42: =Financials!G113 -> % | Q42: =Financials!N113 -> 0.26689476 | R42: =Financials!O113 -> 0.55430096 | S42: =Financials!P113 -> 0.98808983 | T42: =Financials!Q113 -> 1.6839997 | U42: =Financials!R113 -> 2.1854594 | V42: =Financials!S113 -> 3.7562931
C43: =Financials!C87 -> Cash Flow from Investments | E43: =Financials!G87 -> USD | F43: =Financials!N87 -> -1500000 | G43: =Financials!O87 -> 0 | H43: =Financials!P87 -> 0 | I43: =Financials!Q87 -> 0 | J43: =Financials!R87 -> -250000 | K43: =Financials!S87 -> 0 | N43: =Financials!C114 -> Financial Debt/Equity | P43: =Financials!G114 -> % | Q43: =Financials!N114 -> 2.7467951 | R43: =Financials!O114 -> 0.8040741 | S43: =Financials!P114 -> 0.012053737 | T43: =Financials!Q114 -> -0.40617568 | U43: =Financials!R114 -> -0.54243029 | V43: =Financials!S114 -> -0.73378009
C44: =Financials!C93 -> Cash Flow from Financing | E44: =Financials!G93 -> USD | F44: =Financials!N93 -> -277087.5 | G44: =Financials!O93 -> -469747.8 | H44: =Financials!P93 -> -490009.36 | I44: =Financials!Q93 -> -509300.26 | J44: =Financials!R93 -> -510668.66 | K44: =Financials!S93 -> -495510.98
C45: =Financials!C95 -> Change in Cash | E45: =Financials!G95 -> USD | F45: =SUM(F42:F44) -> -129079.04 | G45: =SUM(G42:G44) -> 371699.34 | H45: =SUM(H42:H44) -> 412038.74 | I45: =SUM(I42:I44) -> 462603.86 | J45: =SUM(J42:J44) -> 217003.02 | K45: =SUM(K42:K44) -> 480407.25 | N45: =Financials!C131 -> Profitability
N46: =Financials!C132 -> NOPLAT | P46: =Financials!G132 -> USD | Q46: =Financials!N132 -> 0 | R46: =Financials!O132 -> 600513.51 | S46: =Financials!P132 -> 662427.02 | T46: =Financials!Q132 -> 721105.03 | U46: =Financials!R132 -> 720041.36 | V46: =Financials!S132 -> 663890.77
C47: Financial Ratios | N47: =Financials!C134 -> ROIC | P47: =Financials!G134 -> % | Q47: =Financials!N134 -> 0 | R47: =Financials!O134 -> 0.2876138 | S47: =Financials!P134 -> 0.44169989 | T47: =Financials!Q134 -> 0.58709387 | U47: =Financials!R134 -> 0.6676804 | V47: =Financials!S134 -> 0.734723
C48: =Financials!C111 -> Interest Coverage | E48: =Financials!G111 -> x | F48: =Financials!L111 -> 34.031746 | G48: =Financials!M111 -> 17.972603 | H48: =Financials!O111 -> 17.312101 | I48: =Financials!P111 -> 22.793188 | J48: =Financials!Q111 -> 30.767148 | K48: =Financials!R111 -> 40.423374 | N48: =Financials!C135 -> ROA | P48: =Financials!G135 -> % | Q48: =Financials!N135 -> 0.29423441 | R48: =Financials!O135 -> 0.20107081 | S48: =Financials!P135 -> 0.23388158 | T48: =Financials!Q135 -> 0.23899826 | U48: =Financials!R135 -> 0.22347867 | V48: =Financials!S135 -> 0.19455833
C49: =Financials!C112 -> Debt Service Coverage | E49: =Financials!G112 -> x | F49: =Financials!L112 -> 0.59119318 | G49: =Financials!M112 -> 0.29039063 | H49: =Financials!O112 -> 0.33283883 | I49: =Financials!P112 -> 0.45240323 | J49: =Financials!Q112 -> 0.63424321 | K49: =Financials!R112 -> 0.87778607 | N49: =Financials!C136 -> ROE | P49: =Financials!G136 -> % | Q49: =Financials!N136 -> 0.81503877 | R49: =Financials!O136 -> 0.62054846 | S49: =Financials!P136 -> 0.56177192 | T49: =Financials!Q136 -> 0.43787529 | U49: =Financials!R136 -> 0.3370808 | V49: =Financials!S136 -> 0.25485613
C51: Check | F51: =F28-Financials!N31 -> 0 | G51: =G28-Financials!O31 -> 0 | H51: =H28-Financials!P31 -> 0 | I51: =I28-Financials!Q31 -> 0 | J51: =J28-Financials!R31 -> 0 | K51: =K28-Financials!S31 -> 0 | N51: Check BS | Q51: =Q19-Q32 -> 0 | R51: =R19-R32 -> 0 | S51: =S19-S32 -> 0 | T51: =T19-T32 -> 0 | U51: =U19-U32 -> 0 | V51: =V19-V32 -> 0 | Y51: =SUM(F51:W51) -> 0
N52: Check CF | R52: =SUM(G42:G44)-G45 -> 0 | S52: =SUM(H42:H44)-H45 -> 0 | T52: =SUM(I42:I44)-I45 -> 0 | U52: =SUM(J42:J44)-J45 -> 0 | V52: =SUM(K42:K44)-K45 -> 0 | Y52: =SUM(F52:W52) -> 0
N53: Check Cash | R53: =Q10+G45-R10 -> 0 | S53: =R10+H45-S10 -> 0 | T53: =S10+I45-T10 -> 0 | U53: =T10+J45-U10 -> 0 | V53: =U10+K45-V10 -> 0 | Y53: =SUM(F53:W53) -> 0
C55: Profitability | N55: Balance Sheet
C56: =Assumptions!$G$14 -> USD | K56: % | N56: =Assumptions!$G$14 -> USD
D72: =Financials!C199 -> Revenue | G72: =Financials!C202 -> Net Income/Loss | J72: =Financials!C203 -> ROIC
D73: =Financials!C200 -> EBITDA | G73: =Financials!C201 -> EBITDA Margin % | O73: =Financials!C206 -> Net Working Capital | R73: =Financials!C207 -> Fixed Assets | U73: =Financials!C208 -> Cash
C77: DCF Valuation Summary
C78: ="All amounts in "&Assumptions!$G$14 -> All amounts in USD
A79: =A7+1 -> 2 | C79: Free Cash Flow Forecst | N79: DCF Valuation Result
C80: =Assumptions!$G$14 -> USD | S80: Composition of Enterprise Value
N81: Selected TV Model | P81: Two Stage Value Driver | S81: =Assumptions!$G$14 -> USD
N82: =Assumptions!C60 -> Discount Rate (WACC) | P82: =Assumptions!E60 -> % | Q82: =Assumptions!G60 -> 0.099125
N84: ="DCF Valuation Result @"&FIXED(Assumptions!$G$60*100,1)&"% "&Assumptions!$C$60 -> DCF Valuation Result @9.9% Discount Rate (WACC)
Q85: =DCF!M45 -> 44925
N86: =DCF!C46 -> PV of Terminal Value | P86: =Assumptions!$G$14 -> USD | Q86: =DCF!M46 -> 2862260.7 | R86: =DCF!N46 -> 0.4421726
N87: =DCF!C47 -> PV of Forecast Period | P87: =Assumptions!$G$14 -> USD | Q87: =DCF!M47 -> 3610914.5 | R87: =DCF!N47 -> 0.5578274
N88: =DCF!C48 -> Enterprise Value | P88: =Assumptions!$G$14 -> USD | Q88: =DCF!M48 -> 6473175.1 | R88: =SUM(R86:R87) -> 1
N89: =DCF!C49 -> Financial Debt | P89: =Assumptions!$G$14 -> USD | Q89: =DCF!M49 -> -2000000 | R89: =IFERROR(Q89/Q$88,0) -> -0.30896739
N90: =DCF!C50 -> Cash | P90: =Assumptions!$G$14 -> USD | Q90: =DCF!M50 -> 600000 | R90: =IFERROR(Q90/Q$88,0) -> 0.092690216
N91: =DCF!C51 -> Equity Value | P91: =Assumptions!$G$14 -> USD | Q91: =DCF!M51 -> 5073175.1 | R91: =IFERROR(Q91/Q$88,0) -> 0.78372283
N94: =DCF!C53 -> Implied Multiples | Q94: =DCF!N53 -> 1 | R94: TV Year 5
N95: =DCF!C54 -> EV/Revenue Exit Multiple | P95: =DCF!H54 -> x | Q95: =DCF!N54 -> 1.1441304 | R95: =DCF!R54 -> 0.62201789
N96: =DCF!C55 -> EV/EBITDA Exit Multiple | P96: =DCF!H55 -> x | Q96: =DCF!N55 -> 5.8810441 | R96: =DCF!R55 -> 3.5455867
N97: =DCF!C56 -> EV/EBIT Exit Multiple | P97: =DCF!H56 -> x | Q97: =DCF!N56 -> 8.0845497 | R97: =DCF!R56 -> 4.9474988
N98: =DCF!C57 -> P/E Exit Multiple | P98: =DCF!H57 -> x | Q98: =DCF!N57 -> 8.9659631 | R98: =DCF!R57 -> 9.8560458
N99: =DCF!C58 -> P/B Exit Multiple | P99: =DCF!H58 -> x | Q99: =DCF!N58 -> 5.6009955 | R99: =DCF!R58 -> 2.3061646
D100: =Financials!C211 -> Free Cash Flow to Firm | G100: =Financials!C212 -> Terminal Value (TV) | J100: =Financials!C214 -> Discounted Cash Flows
C103: Terminal Value Models
C104: =Assumptions!$G$14 -> USD
D133: =Financials!C218 -> TV (Year 5) | F133: =Financials!C221 -> Capitalized Earnings | H133: =Financials!C223 -> H-Model | L133: =Financials!C225 -> EV/EBITDA Exit Multiple (6.0x) | Q133: =Financials!C227 -> P/E Exit Multiple (5.0x) | U133: =Financials!C229 -> One Stage Value Driver
D134: =Financials!C219 -> PV of TV (Year 0) | F134: =Financials!C222 -> Gordon Growth | H134: =Financials!C224 -> EV/Revenue Exit Multiple (2.5x) | L134: =Financials!C226 -> EV/EBIT Exit Multiple (7.0x) | Q134: =Financials!C228 -> P/B Exit Multiple (2.0x) | U134: =Financials!C230 -> Two Stage Value Driver

Sheet Assumptions
C2: =Title!$B$5 -> DCF Valuation Model | V2: =Title!#REF!&" "&Title!#REF! -> #REF! | Y2: Check
V3: =Title!#REF! -> #REF! | Y3: =SUM(Y4:Y1048576) -> 0
C5: Assumptions
C6: ="All amounts in "&Assumptions!$G$14 -> All amounts in USD
C7: General Settings | K7: Business Plan Assumptions | M7: =N7-1 -> 2024 | N7: =O7-1 -> 2025 | O7: =P7 -> 2026 | P7: =Q7-1 -> 2026 | Q7: =G15 -> 2027 | R7: =Q7+1 -> 2028 | S7: =R7+1 -> 2029 | T7: =S7+1 -> 2030 | U7: =T7+1 -> 2031
K8: ="Forecast "&E15 -> Forecast Year | M8: =N8-1 -> -2 | N8: =O8-1 -> -1 | O8: 0 | P8: =N8+1 -> 0 | Q8: =O8+1 -> 1 | R8: =Q8+1 -> 2 | S8: =R8+1 -> 3 | T8: =S8+1 -> 4 | U8: =T8+1 -> 5
C9: Valuation Model | E9: DCF Valuation Model
C10: Project | E10: Company Name | K10: =Financials!C7 -> Income Statement
C11: Model Version
K12: Revenue | L12: =$G$14 -> USD | M12: 4500000 | N12: 4750000 | O12: 5000000 | P12: =MROUND(O12*(1+P13),1000) -> 5263000 | Q12: =P12*(1+Q13) -> 5657725 | R12: =Q12*(1+R13) -> 6082054.4 | S12: =R12*(1+S13) -> 6386157.1 | T12: =S12*(1+T13) -> 6705464.9 | U12: =T12*(1+U13) -> 7040738.2 | Y12: =SUM(P12:V12)-Financials!U10 -> 0
C13: Settings | K13: =K12&" Growth" -> Revenue Growth | L13: % | M13: =IFERROR(((M12-L12)/L12),"NA") -> NA | N13: =IFERROR(((N12-M12)/M12),"NA") -> 0.055555556 | O13: =IFERROR(((O12-N12)/N12),"NA") -> 0.052631579 | P13: =O13 -> 0.052631579 | Q13: 0.075 | R13: 0.075 | S13: 0.05 | T13: 0.05 | U13: 0.05
C14: Currency | G14: USD
C15: First Forecast Year | E15: Year | G15: =YEAR(TODAY())+1 -> 2027 | K15: Direct Costs | L15: =$G$14 -> USD | M15: 2000000 | N15: 2300000 | O15: 2500000 | P15: =IFERROR(P12*(1-P17),0) -> 2631500 | Q15: =IFERROR(Q12*(1-Q17),0) -> 3168326 | R15: =IFERROR(R12*(1-R17),0) -> 3405950.5 | S15: =IFERROR(S12*(1-S17),0) -> 3512386.4 | T15: =IFERROR(T12*(1-T17),0) -> 3688005.7 | U15: =IFERROR(U12*(1-U17),0) -> 3872406 | Y15: =SUM(P15:V15)+Financials!U13 -> 0
K16: Gross Profit | L16: =$G$14 -> USD | M16: =M12-M15 -> 2500000 | N16: =N12-N15 -> 2450000 | O16: =O12-O15 -> 2500000 | P16: =P12-P15 -> 2631500 | Q16: =Q12-Q15 -> 2489399 | R16: =R12-R15 -> 2676103.9 | S16: =S12-S15 -> 2873770.7 | T16: =T12-T15 -> 3017459.2 | U16: =U12-U15 -> 3168332.2 | Y16: =SUM(P16:V16)-Financials!U14 -> 0
C17: Other Assumptions | K17: =K16&" Margin %" -> Gross Profit Margin % | L17: % | M17: =IFERROR(M16/M$12,0) -> 0.55555556 | N17: =IFERROR(N16/N$12,0) -> 0.51578947 | O17: =IFERROR(O16/O$12,0) -> 0.5 | P17: =O17 -> 0.5 | Q17: 0.44 | R17: 0.44 | S17: 0.45 | T17: 0.45 | U17: 0.45
C18: Depreciation period | E18: Years | G18: 5
C19: Interest Rate | E19: % | G19: 0.025 | K19: Operating Expenses | L19: =$G$14 -> USD | M19: 1190000 | N19: 1010000 | O19: 1580000 | P19: 1350000 | Q19: =-IFERROR((Q12*Q21)-Q16,0) -> 1388714.3 | R19: =-IFERROR((R12*R21)-R16,0) -> 1492867.9 | S19: =-IFERROR((S12*S21)-S16,0) -> 1612297.3 | T19: =-IFERROR((T12*T21)-T16,0) -> 1757404.1 | U19: =-IFERROR((U12*U21)-U16,0) -> 1933144.5 | Y19: =SUM(P19:V19)+Financials!U17 -> 0
C20: Income Tax Rate | E20: % | G20: 0.25 | K20: EBITDA | L20: =$G$14 -> USD | M20: =M16-M19 -> 1310000 | N20: =N16-N19 -> 1440000 | O20: =O16-O19 -> 920000 | P20: =P16-P19 -> 1281500 | Q20: =Q16-Q19 -> 1100684.7 | R20: =R16-R19 -> 1183236 | S20: =S16-S19 -> 1261473.4 | T20: =T16-T19 -> 1260055.1 | U20: =U16-U19 -> 1235187.7 | Y20: =SUM(P20:V20)-Financials!U18 -> 0
C21: Dividend Payout Ratio | E21: % of Net Income | G21: 0.3 | K21: =K20&" Margin %" -> EBITDA Margin % | L21: % | M21: =IFERROR(M20/M$12,0) -> 0.29111111 | N21: =IFERROR(N20/N$12,0) -> 0.30315789 | O21: =IFERROR(O20/O$12,0) -> 0.184 | P21: =O21 -> 0.184 | Q21: 0.19454545 | R21: 0.19454545 | S21: 0.19753247 | T21: 0.18791466 | U21: 0.1754344
C23: Net Working Capital | K23: Depreciation | L23: =$G$14 -> USD | M23: 100000 | N23: 100000 | O23: 100000 | P23: =-Financials!N21 -> 0 | Q23: =-Financials!O21 -> 300000 | R23: =-Financials!P21 -> 300000 | S23: =-Financials!Q21 -> 300000 | T23: =-Financials!R21 -> 300000 | U23: =-Financials!S21 -> 350000 | Y23: =SUM(P23:V23)+Financials!U21 -> 0
C24: =K33 -> Receivables | E24: ="Days "&K12 -> Days Revenue | G24: 30 | K24: Extraordinary Expenses | L24: =$G$14 -> USD | M24: 0 | N24: 0 | O24: 0 | P24: 0 | Q24: 0 | R24: 0 | S24: 0 | T24: 0 | U24: 0 | Y24: =SUM(P24:V24)+Financials!U25 -> 0
C25: =K34 -> Inventory | E25: ="Days "&K15 -> Days Direct Costs | G25: 15 | K25: Interest Expense | L25: =$G$14 -> USD | M25: =IFERROR(AVERAGE(M49)*$G$19,0) -> 37500 | N25: =IFERROR(AVERAGE(M49:N49)*$G$19,0) -> 39375 | O25: =IFERROR(AVERAGE(N49:O49)*$G$19,0) -> 45625 | P25: =-Financials!N26 -> 50000 | Q25: =-Financials!O26 -> 46250 | R25: =-Financials!P26 -> 38750 | S25: =-Financials!Q26 -> 31250 | T25: =-Financials!R26 -> 23750 | U25: =-Financials!S26 -> 16250 | Y25: =SUM(P25:V25)+Financials!U26 -> 0
C26: =K44 -> Payables | E26: =E25 -> Days Direct Costs | G26: 20 | K26: Income Taxes | L26: =$G$14 -> USD | M26: =IF((M20-SUM(M23:M25))>0,(M20-SUM(M23:M25))*$G$20,0) -> 293125 | N26: =IF((N20-SUM(N23:N25))>0,(N20-SUM(N23:N25))*$G$20,0) -> 325156.25 | O26: =IF((O20-SUM(O23:O25))>0,(O20-SUM(O23:O25))*$G$20,0) -> 193593.75 | P26: =-Financials!N30 -> 307875 | Q26: =-Financials!O30 -> 188608.67 | R26: =-Financials!P30 -> 211121.51 | S26: =-Financials!Q30 -> 232555.84 | T26: =-Financials!R30 -> 234076.29 | U26: =-Financials!S30 -> 217234.42 | Y26: =SUM(P26:V26)+Financials!U30 -> 0
C27: =K35 -> Other Current Assets | E27: ="% of "&K12 -> % of Revenue | G27: 0.005 | K27: Net Income/Loss | L27: =$G$14 -> USD | M27: =M20-SUM(M23:M26) -> 879375 | N27: =N20-SUM(N23:N26) -> 975468.75 | O27: =O20-SUM(O23:O26) -> 580781.25 | P27: =P20-SUM(P23:P26) -> 923625 | Q27: =Q20-SUM(Q23:Q26) -> 565826.01 | R27: =R20-SUM(R23:R26) -> 633364.52 | S27: =S20-SUM(S23:S26) -> 697667.53 | T27: =T20-SUM(T23:T26) -> 702228.86 | U27: =U20-SUM(U23:U26) -> 651703.27 | Y27: =SUM(P27:V27)-Financials!U31 -> 0
C28: =K45 -> Other Current Liabilities | E28: ="% of "&K15 -> % of Direct Costs | G28: 0.005 | K28: =K27&" Margin %" -> Net Income/Loss Margin % | L28: % | M28: =IFERROR(M27/M$12,0) -> 0.19541667 | N28: =IFERROR(N27/N$12,0) -> 0.20536184 | O28: =IFERROR(O27/O$12,0) -> 0.11615625 | P28: =IFERROR(P27/P$12,0) -> 0.17549401 | Q28: =IFERROR(Q27/Q$12,0) -> 0.10000946 | R28: =IFERROR(R27/R$12,0) -> 0.10413661 | S28: =IFERROR(S27/S$12,0) -> 0.10924685 | T28: =IFERROR(T27/T$12,0) -> 0.10472486 | U28: =IFERROR(U27/U$12,0) -> 0.092561782
K30: =Financials!C38 -> Balance Sheet
C31: Discount Rate Estimation - Weighted Average Cost of Capital
K32: Cash | L32: =$G$14 -> USD | M32: 300000 | N32: 450000 | O32: 600000 | P32: =O32 -> 600000 | Q32: =Financials!O41 -> 971699.34 | R32: =Financials!P41 -> 1383738.1 | S32: =Financials!Q41 -> 1846341.9 | T32: =Financials!R41 -> 2063345 | U32: =Financials!S41 -> 2543752.2
C33: Weight | K33: Receivables | L33: =$G$14 -> USD | M33: 600000 | N33: 550000 | O33: 450000 | P33: =Financials!N42 -> 432575.34 | Q33: =Financials!O42 -> 465018.49 | R33: =Financials!P42 -> 498529.05 | S33: =Financials!Q42 -> 524889.62 | T33: =Financials!R42 -> 551134.11 | U33: =Financials!S42 -> 578690.81
C34: Equity | E34: % | G34: 0.65 | K34: Inventory | L34: =$G$14 -> USD | M34: 450000 | N34: 550000 | O34: 350000 | P34: =Financials!N43 -> 108143.84 | Q34: =Financials!O43 -> 130205.18 | R34: =Financials!P43 -> 139588.13 | S34: =Financials!Q43 -> 144344.65 | T34: =Financials!R43 -> 151561.88 | U34: =Financials!S43 -> 159139.97
C35: Debt | E35: % | G35: =1-G34 -> 0.35 | K35: Other Current Assets | L35: =$G$14 -> USD | M35: 40000 | N35: 40000 | O35: 20000 | P35: =Financials!N44 -> 26315 | Q35: =Financials!O44 -> 28288.625 | R35: =Financials!P44 -> 30410.272 | S35: =Financials!Q44 -> 31930.785 | T35: =Financials!R44 -> 33527.325 | U35: =Financials!S44 -> 35203.691
C36: Total | E36: % | G36: =SUM(G34:G35) -> 1 | K36: Current Assets | L36: =$G$14 -> USD | M36: =SUM(M32:M35) -> 1390000 | N36: =SUM(N32:N35) -> 1590000 | O36: =SUM(O32:O35) -> 1420000 | P36: =SUM(P32:P35) -> 1167034.2 | Q36: =SUM(Q32:Q35) -> 1595211.6 | R36: =SUM(R32:R35) -> 2052265.5 | S36: =SUM(S32:S35) -> 2547507 | T36: =SUM(T32:T35) -> 2799568.3 | U36: =SUM(U32:U35) -> 3316786.7
C38: Cost of Equity | K38: Capital Expenditures | L38: =$G$14 -> USD | M38: 1900000 | N38: 2000000 | O38: 2250000 | P38: =Financials!N47 -> 1500000 | Q38: =Financials!O47 -> 1200000 | R38: =Financials!P47 -> 900000 | S38: =Financials!Q47 -> 600000 | T38: =Financials!R47 -> 550000 | U38: =Financials!S47 -> 200000
C39: Risk free interest rate 2) | E39: % | G39: 0.02 | K39: Fixed Assets | L39: =$G$14 -> USD | M39: =M38 -> 1900000 | N39: =N38 -> 2000000 | O39: =O38 -> 2250000 | P39: =P38 -> 1500000 | Q39: =Q38 -> 1200000 | R39: =R38 -> 900000 | S39: =S38 -> 600000 | T39: =T38 -> 550000 | U39: =U38 -> 200000
C40: Beta (unlevered) 3) | E40: % | G40: 1
C41: Beta (levered) 4) | E41: x | G41: =IFERROR(G40*(1+G35/G34),0) -> 1.5384615 | K41: Assets | L41: =$G$14 -> USD | M41: =SUM(M39,M36) -> 3290000 | N41: =SUM(N39,N36) -> 3590000 | O41: =SUM(O39,O36) -> 3670000 | P41: =SUM(P39,P36) -> 2667034.2 | Q41: =SUM(Q39,Q36) -> 2795211.6 | R41: =SUM(R39,R36) -> 2952265.5 | S41: =SUM(S39,S36) -> 3147507 | T41: =SUM(T39,T36) -> 3349568.3 | U41: =SUM(U39,U36) -> 3516786.7
C42: Market Risk Premium USA 5) | E42: % | G42: 0.06
C43: Equity Risk Premium | E43: % | G43: =G41*G42 -> 0.092307692 | K43: Short-Term Provisions | L43: =$G$14 -> USD | M43: 0 | N43: 0 | O43: 0 | P43: =O43 -> 0 | Q43: =P43 -> 0 | R43: =Q43 -> 0 | S43: =R43 -> 0 | T43: =S43 -> 0 | U43: =T43 -> 0
C44: Other Risk Premium | E44: % | G44: 0.02 | K44: Payables | L44: =$G$14 -> USD | M44: 230000 | N44: 330000 | O44: 340000 | P44: =-Financials!N164 -> 144191.78 | Q44: =-Financials!O164 -> 173606.9 | R44: =-Financials!P164 -> 186117.51 | S44: =-Financials!Q164 -> 192459.53 | T44: =-Financials!R164 -> 202082.51 | U44: =-Financials!S164 -> 212186.63
C45: Cost of Equity | E45: % | G45: =G44+G43+G39 -> 0.13230769 | K45: Other Current Liabilities | L45: =$G$14 -> USD | M45: 40000 | N45: 40000 | O45: 10000 | P45: =-Financials!N165 -> 13157.5 | Q45: =-Financials!O165 -> 15841.63 | R45: =-Financials!P165 -> 17029.752 | S45: =-Financials!Q165 -> 17561.932 | T45: =-Financials!R165 -> 18440.029 | U45: =-Financials!S165 -> 19362.03
K46: Short-term Liabilities | L46: =$G$14 -> USD | M46: =SUM(M43:M45) -> 270000 | N46: =SUM(N43:N45) -> 370000 | O46: =SUM(O43:O45) -> 350000 | P46: =SUM(P43:P45) -> 157349.28 | Q46: =SUM(Q43:Q45) -> 189448.53 | R46: =SUM(R43:R45) -> 203147.26 | S46: =SUM(S43:S45) -> 210021.46 | T46: =SUM(T43:T45) -> 220522.53 | U46: =SUM(U43:U45) -> 231548.66
C47: Cost of Debt
C48: Risk free interest rate | E48: % | G48: =G39 -> 0.02 | K48: Long-Term Provisions | L48: =$G$14 -> USD | M48: 0 | N48: 0 | O48: 0 | P48: =O48 -> 0 | Q48: =P48 -> 0 | R48: =Q48 -> 0 | S48: =R48 -> 0 | T48: =S48 -> 0 | U48: =T48 -> 0
C49: Debt risk premium 8) | E49: % | G49: 0.03 | K49: Financial Debt | L49: =$G$14 -> USD | M49: 1500000 | N49: 1650000 | O49: 2000000 | P49: =O49 -> 2000000 | Q49: =P49+Q59 -> 1700000 | R49: =Q49+R59 -> 1400000 | S49: =R49+S59 -> 1100000 | T49: =S49+T59 -> 800000 | U49: =T49+U59 -> 500000
C50: Pre-tax cost of debt | E50: % | G50: =G48+G49 -> 0.05 | K50: Long-term Liabilities | L50: =$G$14 -> USD | M50: =SUM(M48:M49) -> 1500000 | N50: =SUM(N48:N49) -> 1650000 | O50: =SUM(O48:O49) -> 2000000 | P50: =SUM(P48:P49) -> 2000000 | Q50: =SUM(Q48:Q49) -> 1700000 | R50: =SUM(R48:R49) -> 1400000 | S50: =SUM(S48:S49) -> 1100000 | T50: =SUM(T48:T49) -> 800000 | U50: =SUM(U48:U49) -> 500000
C51: Tax rate | E51: % | G51: =G20 -> 0.25
C52: Cost of Debt (after tax) | E52: % | G52: =G50*(1-G51) -> 0.0375 | K52: Shareholder's Equity | L52: =$G$14 -> USD | M52: =M41-SUM(M46,M50) -> 1520000 | N52: =N41-SUM(N46,N50) -> 1570000 | O52: =O41-SUM(O46,O50) -> 1320000 | P52: =Financials!N62 -> 509684.9 | Q52: =Financials!O62 -> 905763.11 | R52: =Financials!P62 -> 1349118.3 | S52: =Financials!Q62 -> 1837485.5 | T52: =Financials!R62 -> 2329045.7 | U52: =Financials!S62 -> 2785238
C54: Discount Rate (WACC) | E54: % | G54: =G45*G34+G52*G35 -> 0.099125 | K54: Liabilities & Shareholder's Equity | L54: =$G$14 -> USD | M54: =SUM(M52,M50,M46) -> 3290000 | N54: =SUM(N52,N50,N46) -> 3590000 | O54: =SUM(O52,O50,O46) -> 3670000 | P54: =SUM(P52,P50,P46) -> 2667034.2 | Q54: =SUM(Q52,Q50,Q46) -> 2795211.6 | R54: =SUM(R52,R50,R46) -> 2952265.5 | S54: =SUM(S52,S50,S46) -> 3147507 | T54: =SUM(T52,T50,T46) -> 3349568.3 | U54: =SUM(U52,U50,U46) -> 3516786.7
K56: =Financials!C71 -> Cash Flow Statement
C57: DCF Valuation Assumptions
K58: ="Change in "&K38 -> Change in Capital Expenditures | L58: =$G$14 -> USD | P58: 1500000 | Q58: 0 | R58: 0 | S58: 0 | T58: 250000 | U58: 0
C59: Discounting Method | E59: Years | G59: Mid-Year | K59: ="Change in "&K49 -> Change in Financial Debt | L59: =$G$14 -> USD | M59: =IFERROR(M49-L49,0) -> 0 | N59: =IFERROR(N49-M49,0) -> 150000 | O59: =IFERROR(O49-N49,0) -> 350000 | P59: =IFERROR(P49-O49,0) -> 0 | Q59: -300000 | R59: -300000 | S59: -300000 | T59: -300000 | U59: -300000
C60: Discount Rate (WACC) | E60: % | G60: =G54 -> 0.099125
K62: Terminal Value Models
C63: Model Checks
K64: Terminal Value Model | M64: ="Terminal Value (Year "&U8&")" -> Terminal Value (Year 5) | N64: Calculations | P64: Explanation
C65: Balance Sheet | G65: =Financials!X65 -> 0 | M65: =$G$14 -> USD
C66: Executive Summary | G66: ='Executive Summary'!Y3 -> 0
C67: Assumptions | G67: =Y3 -> 0 | K67: Capitalized Earnings | M67: ='Terminal Value'!H126 -> 6697511 | N67: =HYPERLINK("#"&CELL("address",'Terminal Value'!$H$18),"=> "&'Terminal Value'!$C$7) -> => Capitalized Earnings | P67: Capitalization of EBIT less Taxes at the Company's Discount Rate
C68: Financials | G68: =Financials!X3 -> 0 | K68: Gordon Growth | M68: ='Terminal Value'!H127 -> 13663519 | N68: =HYPERLINK("#"&CELL("address",'Terminal Value'!$H$37),"=> "&'Terminal Value'!$C$24) -> => Gordon Growth | P68: Capitalized Free Cash Cash Flows which are assumed to grow forever
C69: DCF | G69: =DCF!U3 -> 0 | K69: H-Model | M69: ='Terminal Value'!H128 -> 16867483 | N69: =HYPERLINK("#"&CELL("address",'Terminal Value'!$G$64),"=> "&'Terminal Value'!$C$43) -> => H-Model | P69: 2 Stage Growth Modell (Period of High and Low Growth)
C70: Terminal Value | G70: ='Terminal Value'!U3 -> 0 | K70: =C95&" ("&FIXED(G95,1)&"x)" -> EV/Revenue Exit Multiple (2.5x) | M70: ='Terminal Value'!H129 -> 17601845 | N70: =HYPERLINK("#"&CELL("address",'Terminal Value'!$O$74),"=> "&'Terminal Value'!$C$74) -> => EV/Revenue Exit Multiple | P70: Determines the Terminal Value based on an Exit Multiple
C71: Two Stage Value Driver Model | G71: ='Terminal Value'!U4 -> 0 | K71: =C96&" ("&FIXED(G96,1)&"x)" -> EV/EBITDA Exit Multiple (6.0x) | M71: ='Terminal Value'!H130 -> 7411126.2 | N71: =HYPERLINK("#"&CELL("address",'Terminal Value'!$O$75),"=> "&'Terminal Value'!$C$75) -> => EV/EBITDA Exit Multiple | P71: Determines the Terminal Value based on an Exit Multiple
K72: =C97&" ("&FIXED(G97,1)&"x)" -> EV/EBIT Exit Multiple (7.0x) | M72: ='Terminal Value'!H131 -> 6196313.9 | N72: =HYPERLINK("#"&CELL("address",'Terminal Value'!$O$76),"=> "&'Terminal Value'!$C$76) -> => EV/EBIT Exit Multiple | P72: Determines the Terminal Value based on an Exit Multiple
K73: =C98&" ("&FIXED(G98,1)&"x)" -> P/E Exit Multiple (5.0x) | M73: ='Terminal Value'!H132 -> 1214764.1 | N73: =HYPERLINK("#"&CELL("address",'Terminal Value'!$O$77),"=> "&'Terminal Value'!$C$77) -> => P/E Exit Multiple | P73: Determines the Terminal Value based on an Exit Multiple
K74: =C99&" ("&FIXED(G99,1)&"x)" -> P/B Exit Multiple (2.0x) | M74: ='Terminal Value'!H133 -> 3526723.8 | N74: =HYPERLINK("#"&CELL("address",'Terminal Value'!$O$78),"=> "&'Terminal Value'!$C$78) -> => P/B Exit Multiple | P74: Determines the Terminal Value based on an Exit Multiple
K75: One Stage Value Driver | M75: ='Terminal Value'!H134 -> 965088.18 | N75: =HYPERLINK("#"&CELL("address",'Terminal Value'!$G$106),"=> "&'Terminal Value'!$C$84) -> => One Stage Value Driver | P75: We Model Excess Return into the Future
K76: Two Stage Value Driver | M76: ='Terminal Value'!H135 -> 4379465.1 | N76: =HYPERLINK("#"&CELL("address",'Two Stage Value Driver Model'!$R$47),"=> "&'Two Stage Value Driver Model'!$C$7) -> => Two Stage Value Driver | P76: Models Terminal Value as a Function of ROCE and Growth in Two Stages
C79: Terminal Value Assumptions by Model | R79: Selectors
C81: =K67 -> Capitalized Earnings | K81: =K75 -> One Stage Value Driver | R81: Discounting Period
C82: Capitalization Rate | E82: % | G82: =G60 -> 0.099125 | K82: Discount Rate | L82: % | M82: =$G$60 -> 0.099125 | R82: Mid-Year | T82: 0.5
K83: Spread to Discount Rate | L83: % | M83: 0.02 | R83: End of Year | T83: 1
C84: =K68 -> Gordon Growth | K84: ROIC | L84: % | M84: =M82+M83 -> 0.119125
C85: Discount Rate | E85: % | G85: =$G$60 -> 0.099125 | K85: Growth Rate | L85: % | M85: =G$86 -> 0.025 | R85: ROCE Stage I
C86: Growth Rate | E86: % | G86: 0.025 | R86: Steady Decline
K87: =K76 -> Two Stage Value Driver | R87: Exponential Decline
C88: =K69 -> H-Model | K88: Stages | M88: Stage I | O88: Stage II | R88: Decline Jump at End
C89: High Growth | E89: % | G89: 0.06
C90: Low Growth | E90: % | G90: 0.03 | K90: Timeline
C91: Period of High Growth | E91: Years | G91: 10 | K91: Duration of Competitive Advantage | L91: Years | M91: 15 | O91: NA | R91: Links
K92: Start | L92: Year | M92: 6 | O92: =M92+M91 -> 21 | R92: =HYPERLINK("#"&CELL("address",Terms!$F$21),"Terms and Abbreviationss") -> Terms and Abbreviationss
C93: =G94&"s" -> Exit Multiples | K93: End | L93: Year | M93: =M92+M91-1 -> 20 | O93: Infinite | R93: =HYPERLINK("#"&CELL("address",'Executive Summary'!$F$10),"Executive Summary") -> Executive Summary
C94: Label | G94: Exit Multiple | K94: Discount Rate | L94: % | M94: =$G$60 -> 0.099125 | O94: =M94 -> 0.099125 | R94: =HYPERLINK("#"&CELL("address",Assumptions!$G$14),"Assumptions") -> Assumptions
C95: ="EV/Revenue "&$G$94 -> EV/Revenue Exit Multiple | E95: x | G95: 2.5 | R95: =HYPERLINK("#"&CELL("address",Financials!$K$31),"Financials") -> Financials
C96: ="EV/EBITDA "&$G$94 -> EV/EBITDA Exit Multiple | E96: x | G96: 6 | K96: Value Drivers | R96: =HYPERLINK("#"&CELL("address",DCF!$M$51),"DCF") -> DCF
C97: ="EV/EBIT "&$G$94 -> EV/EBIT Exit Multiple | E97: x | G97: 7 | K97: Growth Rate | L97: % | M97: 0.025 | O97: =G86 -> 0.025 | R97: =HYPERLINK("#"&CELL("address",'Terminal Value'!$H$138),"Terminal Value") -> Terminal Value
C98: ="P/E "&$G$94 -> P/E Exit Multiple | E98: x | G98: 5 | K98: Spread to Discount Rate | L98: % | M98: =M99-M94 -> 0.635598 | O98: 0 | R98: =HYPERLINK("#"&CELL("address",'Two Stage Value Driver Model'!$R$47),"Two Stage Value Driver Model") -> Two Stage Value Driver Model
C99: ="P/B "&$G$94 -> P/B Exit Multiple | E99: x | G99: 2 | K99: ROIC | L99: % | M99: ='Two Stage Value Driver Model'!R15 -> 0.734723 | O99: =O94+O98 -> 0.099125
K100: ROIC Curve | L100: % | M100: ='Two Stage Value Driver Model'!H15 -> Exponential Decline
B105: =Title!#REF! -> #REF!
B106: =Title!#REF! -> #REF!

Sheet Financials
B2: =Title!$B$5 -> DCF Valuation Model | V2: =Title!#REF!&" "&Title!#REF! -> #REF!
V3: =Title!#REF! -> #REF! | X3: =SUM(X4:X168) -> 0
C5: Financial Projections
C6: ="All amounts in "&Assumptions!$G$14 -> All amounts in USD
A7: =MAX(A$1:A6)+1 -> 1 | C7: Income Statement | G7: Unit | K7: =Assumptions!M7 -> 2024 | L7: =Assumptions!N7 -> 2025 | M7: =Assumptions!O7 -> 2026 | N7: =Assumptions!P7 -> 2026 | O7: =Assumptions!Q7 -> 2027 | P7: =Assumptions!R7 -> 2028 | Q7: =Assumptions!S7 -> 2029 | R7: =Assumptions!T7 -> 2030 | S7: =Assumptions!U7 -> 2031 | U7: =MAX(K8:T8) -> 5
C8: =Assumptions!K8 -> Forecast Year | K8: =L8-1 -> -2 | L8: =M8-1 -> -1 | M8: 0 | N8: =L8+1 -> 0 | O8: =M8+1 -> 1 | P8: =O8+1 -> 2 | Q8: =P8+1 -> 3 | R8: =Q8+1 -> 4 | S8: =R8+1 -> 5 | U8: =S8 -> 5
C10: =Assumptions!K12 -> Revenue | G10: =Assumptions!$G$14 -> USD | K10: =Assumptions!M12 -> 4500000 | L10: =Assumptions!N12 -> 4750000 | M10: =Assumptions!O12 -> 5000000 | N10: =Assumptions!P12 -> 5263000 | O10: =Assumptions!Q12 -> 5657725 | P10: =Assumptions!R12 -> 6082054.4 | Q10: =Assumptions!S12 -> 6386157.1 | R10: =Assumptions!T12 -> 6705464.9 | S10: =Assumptions!U12 -> 7040738.2 | U10: =SUM(N10:T10) -> 37135140
C11: =Assumptions!K13 -> Revenue Growth | G11: % | K11: =IFERROR(K10/I10-1,"NA") -> NA | L11: =IFERROR(L10/K10-1,"NA") -> 0.055555556 | M11: =IFERROR(M$10/L$10-1,"NA") -> 0.052631579 | N11: =IFERROR(N$10/M$10-1,"NA") -> 0.0526 | O11: =IFERROR(O$10/N$10-1,"NA") -> 0.075 | P11: =IFERROR(P$10/O$10-1,"NA") -> 0.075 | Q11: =IFERROR(Q$10/P$10-1,"NA") -> 0.05 | R11: =IFERROR(R$10/Q$10-1,"NA") -> 0.05 | S11: =IFERROR(S$10/R$10-1,"NA") -> 0.05 | U11: =IFERROR((O10/P10)^(1/$U$7-$O$8)-1,"NA") -> 0.059562969
C13: =Assumptions!K15 -> Direct Costs | G13: =Assumptions!$G$14 -> USD | K13: =-Assumptions!M15 -> -2000000 | L13: =-Assumptions!N15 -> -2300000 | M13: =-Assumptions!O15 -> -2500000 | N13: =-Assumptions!P15 -> -2631500 | O13: =-Assumptions!Q15 -> -3168326 | P13: =-Assumptions!R15 -> -3405950.5 | Q13: =-Assumptions!S15 -> -3512386.4 | R13: =-Assumptions!T15 -> -3688005.7 | S13: =-Assumptions!U15 -> -3872406 | U13: =SUM(N13:T13) -> -20278575
C14: =Assumptions!K16 -> Gross Profit | G14: =Assumptions!$G$14 -> USD | K14: =K10+K13 -> 2500000 | L14: =L10+L13 -> 2450000 | M14: =M10+M13 -> 2500000 | N14: =N10+N13 -> 2631500 | O14: =O10+O13 -> 2489399 | P14: =P10+P13 -> 2676103.9 | Q14: =Q10+Q13 -> 2873770.7 | R14: =R10+R13 -> 3017459.2 | S14: =S10+S13 -> 3168332.2 | U14: =U10+U13 -> 16856565 | X14: =SUM(K10:S10)+SUM(K13:S13)-SUM(K14:S14) -> 0
C15: =Assumptions!K17 -> Gross Profit Margin % | G15: % of Revenue | K15: =IF(ISERR(K14/K$10),"NA",K14/K$10) -> 0.55555556 | L15: =IF(ISERR(L14/L$10),"NA",L14/L$10) -> 0.51578947 | M15: =IF(ISERR(M$14/M$10),"NA",M$14/M$10) -> 0.5 | N15: =IF(ISERR(N$14/N$10),"NA",N$14/N$10) -> 0.5 | O15: =IF(ISERR(O$14/O$10),"NA",O$14/O$10) -> 0.44 | P15: =IF(ISERR(P$14/P$10),"NA",P$14/P$10) -> 0.44 | Q15: =IF(ISERR(Q$14/Q$10),"NA",Q$14/Q$10) -> 0.45 | R15: =IF(ISERR(R$14/R$10),"NA",R$14/R$10) -> 0.45 | S15: =IF(ISERR(S$14/S$10),"NA",S$14/S$10) -> 0.45 | U15: =IF(ISERR(U$14/U$10),"NA",U$14/U$10) -> 0.45392491
C17: =Assumptions!K19 -> Operating Expenses | G17: =Assumptions!$G$14 -> USD | K17: =-Assumptions!M19 -> -1190000 | L17: =-Assumptions!N19 -> -1010000 | M17: =-Assumptions!O19 -> -1580000 | N17: =-Assumptions!P19 -> -1350000 | O17: =-Assumptions!Q19 -> -1388714.3 | P17: =-Assumptions!R19 -> -1492867.9 | Q17: =-Assumptions!S19 -> -1612297.3 | R17: =-Assumptions!T19 -> -1757404.1 | S17: =-Assumptions!U19 -> -1933144.5 | U17: =SUM(N17:T17) -> -9534428.1
C18: =Assumptions!K20 -> EBITDA | G18: =Assumptions!$G$14 -> USD | K18: =K14+K17 -> 1310000 | L18: =L14+L17 -> 1440000 | M18: =M14+M17 -> 920000 | N18: =N14+N17 -> 1281500 | O18: =O14+O17 -> 1100684.7 | P18: =P14+P17 -> 1183236 | Q18: =Q14+Q17 -> 1261473.4 | R18: =R14+R17 -> 1260055.1 | S18: =S14+S17 -> 1235187.7 | U18: =U14+U17 -> 7322136.9 | X18: =SUM(K14:S14)+SUM(K17:S17)-SUM(K18:S18) -> 0
C19: =Assumptions!K21 -> EBITDA Margin % | G19: % of Revenue | K19: =IF(ISERR(K18/K$10),"NA",K18/K$10) -> 0.29111111 | L19: =IF(ISERR(L18/L$10),"NA",L18/L$10) -> 0.30315789 | M19: =IF(ISERR(M18/M$10),"NA",M18/M$10) -> 0.184 | N19: =IF(ISERR(N18/N$10),"NA",N18/N$10) -> 0.2434923 | O19: =IF(ISERR(O18/O$10),"NA",O18/O$10) -> 0.19454545 | P19: =IF(ISERR(P18/P$10),"NA",P18/P$10) -> 0.19454545 | Q19: =IF(ISERR(Q18/Q$10),"NA",Q18/Q$10) -> 0.19753247 | R19: =IF(ISERR(R18/R$10),"NA",R18/R$10) -> 0.18791466 | S19: =IF(ISERR(S18/S$10),"NA",S18/S$10) -> 0.1754344 | U19: =IF(ISERR(U18/U$10),"NA",U18/U$10) -> 0.19717542
C21: =Assumptions!K23 -> Depreciation | G21: =Assumptions!$G$14 -> USD | K21: =-Assumptions!M23 -> -100000 | L21: =-Assumptions!N23 -> -100000 | M21: =-Assumptions!O23 -> -100000 | N21: =-N185 -> 0 | O21: =-O185 -> -300000 | P21: =-P185 -> -300000 | Q21: =-Q185 -> -300000 | R21: =-R185 -> -300000 | S21: =-S185 -> -350000 | U21: =SUM(N21:T21) -> -1550000 | X21: =U21+U185 -> 0
C22: EBIT | G22: =Assumptions!$G$14 -> USD | K22: =K18+K21 -> 1210000 | L22: =L18+L21 -> 1340000 | M22: =M18+M21 -> 820000 | N22: =N18+N21 -> 1281500 | O22: =O18+O21 -> 800684.68 | P22: =P18+P21 -> 883236.03 | Q22: =Q18+Q21 -> 961473.37 | R22: =R18+R21 -> 960055.14 | S22: =S18+S21 -> 885187.7 | U22: =U18+U21 -> 5772136.9 | X22: =SUM(K18:S18)+SUM(K21:S21)-SUM(K22:S22) -> 0
C23: =C22&" Margin %" -> EBIT Margin % | G23: % of Revenue | K23: =IF(ISERR(K22/K$10),"NA",K22/K$10) -> 0.26888889 | L23: =IF(ISERR(L22/L$10),"NA",L22/L$10) -> 0.28210526 | M23: =IF(ISERR(M22/M$10),"NA",M22/M$10) -> 0.164 | N23: =IF(ISERR(N22/N$10),"NA",N22/N$10) -> 0.2434923 | O23: =IF(ISERR(O22/O$10),"NA",O22/O$10) -> 0.14152061 | P23: =IF(ISERR(P22/P$10),"NA",P22/P$10) -> 0.14522002 | Q23: =IF(ISERR(Q22/Q$10),"NA",Q22/Q$10) -> 0.15055586 | R23: =IF(ISERR(R22/R$10),"NA",R22/R$10) -> 0.14317503 | S23: =IF(ISERR(S22/S$10),"NA",S22/S$10) -> 0.12572371 | U23: =IF(ISERR(U22/U$10),"NA",U22/U$10) -> 0.15543598
C25: =Assumptions!K24 -> Extraordinary Expenses | G25: =Assumptions!$G$14 -> USD | K25: =-Assumptions!M24 -> 0 | L25: =-Assumptions!N24 -> 0 | M25: =-Assumptions!O24 -> 0 | N25: =-Assumptions!P24 -> 0 | O25: =-Assumptions!Q24 -> 0 | P25: 0 | Q25: 0 | R25: 0 | S25: 0 | U25: =SUM(N25:T25) -> 0
C26: =Assumptions!K25 -> Interest Expense | G26: =Assumptions!$G$14 -> USD | K26: =-Assumptions!M25 -> -37500 | L26: =-Assumptions!N25 -> -39375 | M26: =-Assumptions!O25 -> -45625 | N26: =-IFERROR(AVERAGE(N59)*N$115,0) -> -50000 | O26: =-IFERROR(AVERAGE(N59:O59)*O$115,0) -> -46250 | P26: =-IFERROR(AVERAGE(O59:P59)*P$115,0) -> -38750 | Q26: =-IFERROR(AVERAGE(P59:Q59)*Q$115,0) -> -31250 | R26: =-IFERROR(AVERAGE(Q59:R59)*R$115,0) -> -23750 | S26: =-IFERROR(AVERAGE(R59:S59)*S$115,0) -> -16250 | U26: =SUM(N26:T26) -> -206250
C27: EBT | G27: =Assumptions!$G$14 -> USD | K27: =K22+SUM(K25:K26) -> 1172500 | L27: =L22+SUM(L25:L26) -> 1300625 | M27: =M22+SUM(M25:M26) -> 774375 | N27: =N22+SUM(N25:N26) -> 1231500 | O27: =O22+SUM(O25:O26) -> 754434.68 | P27: =P22+SUM(P25:P26) -> 844486.03 | Q27: =Q22+SUM(Q25:Q26) -> 930223.37 | R27: =R22+SUM(R25:R26) -> 936305.14 | S27: =S22+SUM(S25:S26) -> 868937.7 | U27: =U22+SUM(U25:U26) -> 5565886.9 | X27: =SUM(K22:S22)+SUM(K25:S26)-SUM(K27:S27) -> 0
C28: =C27&" Margin %" -> EBT Margin % | G28: % of Revenue | K28: =IF(ISERR(K27/K$10),"NA",K27/K$10) -> 0.26055556 | L28: =IF(ISERR(L27/L$10),"NA",L27/L$10) -> 0.27381579 | M28: =IF(ISERR(M27/M$10),"NA",M27/M$10) -> 0.154875 | N28: =IF(ISERR(N27/N$10),"NA",N27/N$10) -> 0.23399202 | O28: =IF(ISERR(O27/O$10),"NA",O27/O$10) -> 0.13334594 | P28: =IF(ISERR(P27/P$10),"NA",P27/P$10) -> 0.13884881 | Q28: =IF(ISERR(Q27/Q$10),"NA",Q27/Q$10) -> 0.14566246 | R28: =IF(ISERR(R27/R$10),"NA",R27/R$10) -> 0.13963314 | S28: =IF(ISERR(S27/S$10),"NA",S27/S$10) -> 0.12341571 | U28: =IF(ISERR(U27/U$10),"NA",U27/U$10) -> 0.14988194
C30: =Assumptions!K26 -> Income Taxes | G30: =Assumptions!$G$14 -> USD | K30: =-Assumptions!M26 -> -293125 | L30: =-Assumptions!N26 -> -325156.25 | M30: =-Assumptions!O26 -> -193593.75 | N30: =IF(N27>0,-N27*N$145,0) -> -307875 | O30: =IF(O27>0,-O27*O$145,0) -> -188608.67 | P30: =IF(P27>0,-P27*P$145,0) -> -211121.51 | Q30: =IF(Q27>0,-Q27*Q$145,0) -> -232555.84 | R30: =IF(R27>0,-R27*R$145,0) -> -234076.29 | S30: =IF(S27>0,-S27*S$145,0) -> -217234.42 | U30: =SUM(N30:T30) -> -1391471.7
C31: =Assumptions!K27 -> Net Income/Loss | G31: =Assumptions!$G$14 -> USD | K31: =K27+K30 -> 879375 | L31: =L27+L30 -> 975468.75 | M31: =M27+M30 -> 580781.25 | N31: =N27+N30 -> 923625 | O31: =O27+O30 -> 565826.01 | P31: =P27+P30 -> 633364.52 | Q31: =Q27+Q30 -> 697667.53 | R31: =R27+R30 -> 702228.86 | S31: =S27+S30 -> 651703.27 | U31: =U27+U30 -> 4174415.2 | X31: =SUM(K27:S27)+SUM(K30:S30)-SUM(K31:S31) -> 0
C32: =C31&" Margin %" -> Net Income/Loss Margin % | G32: % of Revenue | K32: =IF(ISERR(K31/K$10),"NA",K31/K$10) -> 0.19541667 | L32: =IF(ISERR(L31/L$10),"NA",L31/L$10) -> 0.20536184 | M32: =IF(ISERR(M31/M$10),"NA",M31/M$10) -> 0.11615625 | N32: =IF(ISERR(N31/N$10),"NA",N31/N$10) -> 0.17549401 | O32: =IF(ISERR(O31/O$10),"NA",O31/O$10) -> 0.10000946 | P32: =IF(ISERR(P31/P$10),"NA",P31/P$10) -> 0.10413661 | Q32: =IF(ISERR(Q31/Q$10),"NA",Q31/Q$10) -> 0.10924685 | R32: =IF(ISERR(R31/R$10),"NA",R31/R$10) -> 0.10472486 | S32: =IF(ISERR(S31/S$10),"NA",S31/S$10) -> 0.092561782 | U32: =IF(ISERR(U31/U$10),"NA",U31/U$10) -> 0.11241146
C33: Check | K33: =K31-Assumptions!M27 -> 0 | L33: =L31-Assumptions!N27 -> 0 | M33: =M31-Assumptions!O27 -> 0 | N33: =N31-Assumptions!P27 -> 0 | O33: =O31-Assumptions!Q27 -> 0 | P33: =P31-Assumptions!R27 -> 0 | Q33: =Q31-Assumptions!S27 -> 0 | R33: =R31-Assumptions!T27 -> 0 | S33: =S31-Assumptions!U27 -> 0 | X33: =SUM(K33:S33) -> 0
C37: ="All amounts in "&Assumptions!$G$14 -> All amounts in USD
A38: =MAX(A$1:A37)+1 -> 2 | C38: Balance Sheet | G38: Unit | K38: =K$7 -> 2024 | L38: =L$7 -> 2025 | M38: =M$7 -> 2026 | N38: =N$7 -> 2026 | O38: =O$7 -> 2027 | P38: =P$7 -> 2028 | Q38: =Q$7 -> 2029 | R38: =R$7 -> 2030 | S38: =S$7 -> 2031 | U38: =U$7 -> 5
C39: =C$8 -> Forecast Year | K39: =K$8 -> -2 | L39: =L$8 -> -1 | M39: =M$8 -> 0 | N39: =N$8 -> 0 | O39: =O$8 -> 1 | P39: =P$8 -> 2 | Q39: =Q$8 -> 3 | R39: =R$8 -> 4 | S39: =S$8 -> 5 | U39: =U$8 -> 5
C41: =Assumptions!K32 -> Cash | G41: =Assumptions!$G$14 -> USD | K41: =Assumptions!M32 -> 300000 | L41: =Assumptions!N32 -> 450000 | M41: =Assumptions!O32 -> 600000 | N41: =N98 -> 600000 | O41: =O98 -> 971699.34 | P41: =P98 -> 1383738.1 | Q41: =Q98 -> 1846341.9 | R41: =R98 -> 2063345 | S41: =S98 -> 2543752.2 | U41: =S41 -> 2543752.2 | X41: =U41-Assumptions!U32 -> 0
C42: =Assumptions!K33 -> Receivables | G42: =Assumptions!$G$14 -> USD | K42: =Assumptions!M33 -> 600000 | L42: =Assumptions!N33 -> 550000 | M42: =Assumptions!O33 -> 450000 | N42: =N160 -> 432575.34 | O42: =O160 -> 465018.49 | P42: =P160 -> 498529.05 | Q42: =Q160 -> 524889.62 | R42: =R160 -> 551134.11 | S42: =S160 -> 578690.81 | U42: =S42 -> 578690.81 | X42: =U42-Assumptions!U33 -> 0
C43: =Assumptions!K34 -> Inventory | G43: =Assumptions!$G$14 -> USD | K43: =Assumptions!M34 -> 450000 | L43: =Assumptions!N34 -> 550000 | M43: =Assumptions!O34 -> 350000 | N43: =N161 -> 108143.84 | O43: =O161 -> 130205.18 | P43: =P161 -> 139588.13 | Q43: =Q161 -> 144344.65 | R43: =R161 -> 151561.88 | S43: =S161 -> 159139.97 | U43: =S43 -> 159139.97 | X43: =U43-Assumptions!U34 -> 0
C44: =Assumptions!K35 -> Other Current Assets | G44: =Assumptions!$G$14 -> USD | K44: =Assumptions!M35 -> 40000 | L44: =Assumptions!N35 -> 40000 | M44: =Assumptions!O35 -> 20000 | N44: =N162 -> 26315 | O44: =O162 -> 28288.625 | P44: =P162 -> 30410.272 | Q44: =Q162 -> 31930.785 | R44: =R162 -> 33527.325 | S44: =S162 -> 35203.691 | U44: =S44 -> 35203.691 | X44: =U44-Assumptions!U35 -> 0
C45: =Assumptions!K36 -> Current Assets | G45: =Assumptions!$G$14 -> USD | K45: =SUM(K41:K44) -> 1390000 | L45: =SUM(L41:L44) -> 1590000 | M45: =SUM(M41:M44) -> 1420000 | N45: =SUM(N41:N44) -> 1167034.2 | O45: =SUM(O41:O44) -> 1595211.6 | P45: =SUM(P41:P44) -> 2052265.5 | Q45: =SUM(Q41:Q44) -> 2547507 | R45: =SUM(R41:R44) -> 2799568.3 | S45: =SUM(S41:S44) -> 3316786.7 | U45: =SUM(U41:U44) -> 3316786.7 | X45: =U45-Assumptions!U36 -> 0
C47: =Assumptions!K38 -> Capital Expenditures | G47: =Assumptions!$G$14 -> USD | K47: =Assumptions!M38 -> 1900000 | L47: =Assumptions!N38 -> 2000000 | M47: =Assumptions!O38 -> 2250000 | N47: =N189 -> 1500000 | O47: =O189 -> 1200000 | P47: =P189 -> 900000 | Q47: =Q189 -> 600000 | R47: =R189 -> 550000 | S47: =S189 -> 200000 | U47: =U189 -> 200000 | X47: =U47-Assumptions!U38 -> 0
C48: =Assumptions!K39 -> Fixed Assets | G48: =Assumptions!$G$14 -> USD | K48: =SUM(K47) -> 1900000 | L48: =SUM(L47) -> 2000000 | M48: =SUM(M47) -> 2250000 | N48: =SUM(N47) -> 1500000 | O48: =SUM(O47) -> 1200000 | P48: =SUM(P47) -> 900000 | Q48: =SUM(Q47) -> 600000 | R48: =SUM(R47) -> 550000 | S48: =SUM(S47) -> 200000 | U48: =SUM(U47) -> 200000 | X48: =U48-Assumptions!U39 -> 0
C50: Assets | G50: =Assumptions!$G$14 -> USD | K50: =SUM(K48,K45) -> 3290000 | L50: =SUM(L48,L45) -> 3590000 | M50: =SUM(M48,M45) -> 3670000 | N50: =SUM(N48,N45) -> 2667034.2 | O50: =SUM(O48,O45) -> 2795211.6 | P50: =SUM(P48,P45) -> 2952265.5 | Q50: =SUM(Q48,Q45) -> 3147507 | R50: =SUM(R48,R45) -> 3349568.3 | S50: =SUM(S48,S45) -> 3516786.7 | U50: =SUM(U48,U45) -> 3516786.7 | X50: =U50-Assumptions!U41 -> 0
C53: =Assumptions!K43 -> Short-Term Provisions | G53: =Assumptions!$G$14 -> USD | K53: =Assumptions!M43 -> 0 | L53: =Assumptions!N43 -> 0 | M53: =Assumptions!O43 -> 0 | N53: =Assumptions!P43 -> 0 | O53: =Assumptions!Q43 -> 0 | P53: =Assumptions!R43 -> 0 | Q53: =Assumptions!S43 -> 0 | R53: =Assumptions!T43 -> 0 | S53: =Assumptions!U43 -> 0 | U53: =S53 -> 0 | X53: =U53-Assumptions!U43 -> 0
C54: =Assumptions!K44 -> Payables | G54: =Assumptions!$G$14 -> USD | K54: =Assumptions!M44 -> 230000 | L54: =Assumptions!N44 -> 330000 | M54: =Assumptions!O44 -> 340000 | N54: =-N164 -> 144191.78 | O54: =-O164 -> 173606.9 | P54: =-P164 -> 186117.51 | Q54: =-Q164 -> 192459.53 | R54: =-R164 -> 202082.51 | S54: =-S164 -> 212186.63 | U54: =S54 -> 212186.63 | X54: =U54-Assumptions!U44 -> 0
C55: =Assumptions!K45 -> Other Current Liabilities | G55: =Assumptions!$G$14 -> USD | K55: =Assumptions!M45 -> 40000 | L55: =Assumptions!N45 -> 40000 | M55: =Assumptions!O45 -> 10000 | N55: =-N165 -> 13157.5 | O55: =-O165 -> 15841.63 | P55: =-P165 -> 17029.752 | Q55: =-Q165 -> 17561.932 | R55: =-R165 -> 18440.029 | S55: =-S165 -> 19362.03 | U55: =S55 -> 19362.03 | X55: =U55-Assumptions!U45 -> 0
C56: =Assumptions!K46 -> Short-term Liabilities | G56: =Assumptions!$G$14 -> USD | K56: =SUM(K53:K55) -> 270000 | L56: =SUM(L53:L55) -> 370000 | M56: =SUM(M53:M55) -> 350000 | N56: =SUM(N53:N55) -> 157349.28 | O56: =SUM(O53:O55) -> 189448.53 | P56: =SUM(P53:P55) -> 203147.26 | Q56: =SUM(Q53:Q55) -> 210021.46 | R56: =SUM(R53:R55) -> 220522.53 | S56: =SUM(S53:S55) -> 231548.66 | U56: =SUM(U53:U55) -> 231548.66 | X56: =U56-Assumptions!U46 -> 0
C58: =Assumptions!K48 -> Long-Term Provisions | G58: =Assumptions!$G$14 -> USD | K58: =Assumptions!M48 -> 0 | L58: =Assumptions!N48 -> 0 | M58: =Assumptions!O48 -> 0 | N58: =Assumptions!P48 -> 0 | O58: =Assumptions!Q48 -> 0 | P58: =Assumptions!R48 -> 0 | Q58: =Assumptions!S48 -> 0 | R58: =Assumptions!T48 -> 0 | S58: =Assumptions!U48 -> 0 | U58: =S58 -> 0 | X58: =U58-Assumptions!U48 -> 0
C59: =Assumptions!K49 -> Financial Debt | G59: =Assumptions!$G$14 -> USD | K59: =Assumptions!M49 -> 1500000 | L59: =Assumptions!N49 -> 1650000 | M59: =Assumptions!O49 -> 2000000 | N59: =Assumptions!P49 -> 2000000 | O59: =Assumptions!Q49 -> 1700000 | P59: =Assumptions!R49 -> 1400000 | Q59: =Assumptions!S49 -> 1100000 | R59: =Assumptions!T49 -> 800000 | S59: =Assumptions!U49 -> 500000 | U59: =S59 -> 500000 | X59: =U59-Assumptions!U49 -> 0
C60: =Assumptions!K50 -> Long-term Liabilities | G60: =Assumptions!$G$14 -> USD | K60: =SUM(K58:K59) -> 1500000 | L60: =SUM(L58:L59) -> 1650000 | M60: =SUM(M58:M59) -> 2000000 | N60: =SUM(N58:N59) -> 2000000 | O60: =SUM(O58:O59) -> 1700000 | P60: =SUM(P58:P59) -> 1400000 | Q60: =SUM(Q58:Q59) -> 1100000 | R60: =SUM(R58:R59) -> 800000 | S60: =SUM(S58:S59) -> 500000 | U60: =SUM(U58:U59) -> 500000 | X60: =U60-Assumptions!U50 -> 0
C62: =Assumptions!K52 -> Shareholder's Equity | G62: =Assumptions!$G$14 -> USD | K62: =K50-SUM(K60,K56) -> 1520000 | L62: =L50-SUM(L60,L56) -> 1570000 | M62: =M50-SUM(M60,M56) -> 1320000 | N62: =N50-SUM(N56,N60) -> 509684.9 | O62: =N62+O31+O92 -> 905763.11 | P62: =O62+P31+P92 -> 1349118.3 | Q62: =P62+Q31+Q92 -> 1837485.5 | R62: =Q62+R31+R92 -> 2329045.7 | S62: =R62+S31+S92 -> 2785238 | U62: =S62 -> 2785238 | X62: =U62-Assumptions!U52 -> 0
C64: =Assumptions!K54 -> Liabilities & Shareholder's Equity | G64: =Assumptions!$G$14 -> USD | K64: =SUM(K62,K60,K56) -> 3290000 | L64: =SUM(L62,L60,L56) -> 3590000 | M64: =SUM(M62,M60,M56) -> 3670000 | N64: =SUM(N62,N60,N56) -> 2667034.2 | O64: =SUM(O62,O60,O56) -> 2795211.6 | P64: =SUM(P62,P60,P56) -> 2952265.5 | Q64: =SUM(Q62,Q60,Q56) -> 3147507 | R64: =SUM(R62,R60,R56) -> 3349568.3 | S64: =SUM(S62,S60,S56) -> 3516786.7 | U64: =SUM(U62,U60,U56) -> 3516786.7 | X64: =U64-Assumptions!U54 -> 0
C65: Check | K65: =K50-K64 -> 0 | L65: =L50-L64 -> 0 | M65: =M50-M64 -> 0 | N65: =N50-N64 -> 0 | O65: =O50-O64 -> 0 | P65: =P50-P64 -> 0 | Q65: =Q50-Q64 -> 0 | R65: =R50-R64 -> 0 | S65: =S50-S64 -> 0 | U65: =U50-U64 -> 0 | X65: =SUM(K65:V65) -> 0
C70: ="All amounts in "&Assumptions!$G$14 -> All amounts in USD
A71: =MAX(A$1:A70)+1 -> 3 | C71: Cash Flow Statement | G71: Unit | K71: =K$7 -> 2024 | L71: =L$7 -> 2025 | M71: =M$7 -> 2026 | N71: =N$7 -> 2026 | O71: =O$7 -> 2027 | P71: =P$7 -> 2028 | Q71: =Q$7 -> 2029 | R71: =R$7 -> 2030 | S71: =S$7 -> 2031 | U71: =U$7 -> 5
C72: =C$8 -> Forecast Year | K72: =K$8 -> -2 | L72: =L$8 -> -1 | M72: =M$8 -> 0 | N72: =N$8 -> 0 | O72: =O$8 -> 1 | P72: =P$8 -> 2 | Q72: =Q$8 -> 3 | R72: =R$8 -> 4 | S72: =S$8 -> 5 | U72: =U$8 -> 5
C74: Cash Flow from Operations
C75: =C31 -> Net Income/Loss | G75: =Assumptions!$G$14 -> USD | N75: =N31 -> 923625 | O75: =O31 -> 565826.01 | P75: =P31 -> 633364.52 | Q75: =Q31 -> 697667.53 | R75: =R31 -> 702228.86 | S75: =S31 -> 651703.27 | U75: =SUM(N75:T75) -> 4174415.2 | X75: =U75-U31 -> 0
C76: ="Addback "&C21 -> Addback Depreciation | G76: =Assumptions!$G$14 -> USD | N76: =-N21 -> 0 | O76: =-O21 -> 300000 | P76: =-P21 -> 300000 | Q76: =-Q21 -> 300000 | R76: =-R21 -> 300000 | S76: =-S21 -> 350000 | U76: =SUM(N76:T76) -> 1550000 | X76: =U76+U21 -> 0
C77: ="Change in "&C42 -> Change in Receivables | G77: =Assumptions!$G$14 -> USD | N77: =N160 -> 432575.34 | O77: =N160-O160 -> -32443.151 | P77: =O160-P160 -> -33510.554 | Q77: =P160-Q160 -> -26360.577 | R77: =Q160-R160 -> -26244.481 | S77: =R160-S160 -> -27556.705 | U77: =SUM(N77:T77) -> 286459.87
C78: ="Change in "&C43 -> Change in Inventory | G78: =Assumptions!$G$14 -> USD | N78: =N161 -> 108143.84 | O78: =N161-O161 -> -22061.342 | P78: =O161-P161 -> -9382.9551 | Q78: =P161-Q161 -> -4756.5134 | R78: =Q161-R161 -> -7217.2323 | S78: =R161-S161 -> -7578.0939 | U78: =SUM(N78:T78) -> 57147.698
C79: ="Change in "&C44 -> Change in Other Current Assets | G79: =Assumptions!$G$14 -> USD | N79: =N162 -> 26315 | O79: =N162-O162 -> -1973.625 | P79: =O162-P162 -> -2121.6469 | Q79: =P162-Q162 -> -1520.5136 | R79: =Q162-R162 -> -1596.5393 | S79: =R162-S162 -> -1676.3662 | U79: =SUM(N79:T79) -> 17426.309
C80: ="Change in "&C53 -> Change in Short-Term Provisions | G80: =Assumptions!$G$14 -> USD | N80: =-N163 -> 0 | O80: =O163-N163 -> 0 | P80: =P163-O163 -> 0 | Q80: =Q163-P163 -> 0 | R80: =R163-Q163 -> 0 | S80: =S163-R163 -> 0 | U80: =SUM(N80:T80) -> 0
C81: ="Change in "&C54 -> Change in Payables | G81: =Assumptions!$G$14 -> USD | N81: =N54 -> 144191.78 | O81: =O54-N54 -> 29415.123 | P81: =P54-O54 -> 12510.607 | Q81: =Q54-P54 -> 6342.0179 | R81: =R54-Q54 -> 9622.9764 | S81: =S54-R54 -> 10104.125 | U81: =SUM(N81:T81) -> 212186.63
C82: ="Change in "&C55 -> Change in Other Current Liabilities | G82: =Assumptions!$G$14 -> USD | N82: =N55 -> 13157.5 | O82: =O55-N55 -> 2684.13 | P82: =P55-O55 -> 1188.1222 | Q82: =Q55-P55 -> 532.17976 | R82: =R55-Q55 -> 878.0966 | S82: =S55-R55 -> 922.00143 | U82: =SUM(N82:T82) -> 19362.03
C83: =C74 -> Cash Flow from Operations | G83: =Assumptions!$G$14 -> USD | N83: =SUM(N75:N82) -> 1648008.5 | O83: =SUM(O75:O82) -> 841447.15 | P83: =SUM(P75:P82) -> 902048.1 | Q83: =SUM(Q75:Q82) -> 971904.12 | R83: =SUM(R75:R82) -> 977671.68 | S83: =SUM(S75:S82) -> 975918.23 | U83: =SUM(U75:U82) -> 6316997.7 | X83: =SUM(O75:S82)-SUM(O83:S83) -> 0
C85: Cash Flow from Investments
C86: =C47 -> Capital Expenditures | G86: =Assumptions!$G$14 -> USD | N86: =-N176 -> -1500000 | O86: =-O176 -> 0 | P86: =-P176 -> 0 | Q86: =-Q176 -> 0 | R86: =-R176 -> -250000 | S86: =-S176 -> 0 | U86: =SUM(N86:T86) -> -1750000
C87: =C85 -> Cash Flow from Investments | G87: =Assumptions!$G$14 -> USD | N87: =SUM(N86:N86) -> -1500000 | O87: =SUM(O86:O86) -> 0 | P87: =SUM(P86:P86) -> 0 | Q87: =SUM(Q86:Q86) -> 0 | R87: =SUM(R86:R86) -> -250000 | S87: =SUM(S86:S86) -> 0 | U87: =SUM(U86:U86) -> -1750000
C89: Cash Flow from Financing
C90: ="Change in "&C58 -> Change in Long-Term Provisions | G90: =Assumptions!$G$14 -> USD | N90: =-N58 -> 0 | O90: =O58-N58 -> 0 | P90: =P58-O58 -> 0 | Q90: =Q58-P58 -> 0 | R90: =R58-Q58 -> 0 | S90: =S58-R58 -> 0 | U90: =SUM(N90:T90) -> 0
C91: ="Change in "&C59 -> Change in Financial Debt | G91: =Assumptions!$G$14 -> USD | N91: =Assumptions!P59 -> 0 | O91: =Assumptions!Q59 -> -300000 | P91: =Assumptions!R59 -> -300000 | Q91: =Assumptions!S59 -> -300000 | R91: =Assumptions!T59 -> -300000 | S91: =Assumptions!U59 -> -300000 | U91: =SUM(N91:T91) -> -1500000
C92: Dividends | G92: =Assumptions!$G$14 -> USD | N92: =MIN(-N75*Assumptions!$G$21,0) -> -277087.5 | O92: =MIN(-O75*Assumptions!$G$21,0) -> -169747.8 | P92: =MIN(-P75*Assumptions!$G$21,0) -> -190009.36 | Q92: =MIN(-Q75*Assumptions!$G$21,0) -> -209300.26 | R92: =MIN(-R75*Assumptions!$G$21,0) -> -210668.66 | S92: =MIN(-S75*Assumptions!$G$21,0) -> -195510.98 | U92: =SUM(N92:T92) -> -1252324.6
C93: =C89 -> Cash Flow from Financing | G93: =Assumptions!$G$14 -> USD | N93: =SUM(N91:N92) -> -277087.5 | O93: =SUM(O91:O92) -> -469747.8 | P93: =SUM(P91:P92) -> -490009.36 | Q93: =SUM(Q91:Q92) -> -509300.26 | R93: =SUM(R91:R92) -> -510668.66 | S93: =SUM(S91:S92) -> -495510.98 | U93: =SUM(U91:U92) -> -2752324.6 | X93: =SUM(O91:S92)-SUM(O93:S93) -> 0
C95: Change in Cash | G95: =Assumptions!$G$14 -> USD | N95: =N83+N87+N93 -> -129079.04 | O95: =O83+O87+O93 -> 371699.34 | P95: =P83+P87+P93 -> 412038.74 | Q95: =Q83+Q87+Q93 -> 462603.86 | R95: =R83+R87+R93 -> 217003.02 | S95: =S83+S87+S93 -> 480407.25 | U95: =U83+U87+U93 -> 1814673.2 | X95: =SUM(O83:S83)+SUM(O87:S87)+SUM(O93:S93)-SUM(O95:S95) -> 0
C97: Cash Beginning | G97: =Assumptions!$G$14 -> USD | N97: =N98-N95 -> 729079.04 | O97: =N98 -> 600000 | P97: =O98 -> 971699.34 | Q97: =P98 -> 1383738.1 | R97: =Q98 -> 1846341.9 | S97: =R98 -> 2063345 | U97: =N97 -> 729079.04
C98: Cash End | G98: =Assumptions!$G$14 -> USD | N98: =Assumptions!P32 -> 600000 | O98: =O95+O97 -> 971699.34 | P98: =P95+P97 -> 1383738.1 | Q98: =Q95+Q97 -> 1846341.9 | R98: =R95+R97 -> 2063345 | S98: =S95+S97 -> 2543752.2 | U98: =U95+U97 -> 2543752.2
C99: Check | N99: =N41-N98 -> 0 | O99: =O41-O98 -> 0 | P99: =P41-P98 -> 0 | Q99: =Q41-Q98 -> 0 | R99: =R41-R98 -> 0 | S99: =S41-S98 -> 0 | U99: =U41-U98 -> 0 | X99: =SUM(J99:S99) -> 0
C103: Financial Ratios
C104: ="All amounts in "&Assumptions!$G$14 -> All amounts in USD
A105: =MAX(A$1:A104)+1 -> 4 | C105: =C103 -> Financial Ratios | G105: Unit | K105: =K$7 -> 2024 | L105: =L$7 -> 2025 | M105: =M$7 -> 2026 | N105: =N$7 -> 2026 | O105: =O$7 -> 2027 | P105: =P$7 -> 2028 | Q105: =Q$7 -> 2029 | R105: =R$7 -> 2030 | S105: =S$7 -> 2031 | U105: =U$7 -> 5
C106: =C$8 -> Forecast Year | K106: =K$8 -> -2 | L106: =L$8 -> -1 | M106: =M$8 -> 0 | N106: =N$8 -> 0 | O106: =O$8 -> 1 | P106: =P$8 -> 2 | Q106: =Q$8 -> 3 | R106: =R$8 -> 4 | S106: =S$8 -> 5 | U106: =U$8 -> 5
C107: Days per Year | K107: =DATE(K105,12,31)-DATE(K105,1,1)+1 -> 366 | L107: =DATE(L105,12,31)-DATE(L105,1,1)+1 -> 365 | M107: =DATE(M105,12,31)-DATE(M105,1,1)+1 -> 365 | N107: =DATE(N105,12,31)-DATE(N105,1,1)+1 -> 365 | O107: =DATE(O105,12,31)-DATE(O105,1,1)+1 -> 365 | P107: =DATE(P105,12,31)-DATE(P105,1,1)+1 -> 366 | Q107: =DATE(Q105,12,31)-DATE(Q105,1,1)+1 -> 365 | R107: =DATE(R105,12,31)-DATE(R105,1,1)+1 -> 365 | S107: =DATE(S105,12,31)-DATE(S105,1,1)+1 -> 365 | U107: =S107 -> 365
C109: Bank Ratios
C110: Financial Debt/EBITDA | G110: x | K110: =IFERROR(K150/K18,"NA") -> 1.1450382 | L110: =IFERROR(L150/L18,"NA") -> 1.1458333 | M110: =IFERROR(M150/M18,"NA") -> 2.173913 | N110: =IFERROR(N150/N18,"NA") -> 1.5606711 | O110: =IFERROR(O150/O18,"NA") -> 1.5444932 | P110: =IFERROR(P150/P18,"NA") -> 1.1831959 | Q110: =IFERROR(Q150/Q18,"NA") -> 0.87199621 | R110: =IFERROR(R150/R18,"NA") -> 0.63489285 | S110: =IFERROR(S150/S18,"NA") -> 0.40479678 | U110: =IFERROR(U150/U18,"NA") -> 0.068286076
C111: Interest Coverage | G111: x | K111: =IFERROR(K22/-K26,"NA") -> 32.266667 | L111: =IFERROR(L22/-L26,"NA") -> 34.031746 | M111: =IFERROR(M22/-M26,"NA") -> 17.972603 | N111: =IFERROR(N22/-N26,"NA") -> 25.63 | O111: =IFERROR(O22/-O26,"NA") -> 17.312101 | P111: =IFERROR(P22/-P26,"NA") -> 22.793188 | Q111: =IFERROR(Q22/-Q26,"NA") -> 30.767148 | R111: =IFERROR(R22/-R26,"NA") -> 40.423374 | S111: =IFERROR(S22/-S26,"NA") -> 54.473089 | U111: =IFERROR(U22/-U26,"NA") -> 27.986118
C112: Debt Service Coverage | G112: x | K112: =IFERROR(K31/K59,"NA") -> 0.58625 | L112: =IFERROR(L31/L59,"NA") -> 0.59119318 | M112: =IFERROR(M31/M59,"NA") -> 0.29039063 | N112: =IFERROR(N31/N59,"NA") -> 0.4618125 | O112: =IFERROR(O31/O59,"NA") -> 0.33283883 | P112: =IFERROR(P31/P59,"NA") -> 0.45240323 | Q112: =IFERROR(Q31/Q59,"NA") -> 0.63424321 | R112: =IFERROR(R31/R59,"NA") -> 0.87778607 | S112: =IFERROR(S31/S59,"NA") -> 1.3034065 | U112: =IFERROR(U31/U59,"NA") -> 8.3488304
C113: Equity % | G113: % | K113: =IFERROR(K148/K152,"NA") -> 0.55882353 | L113: =IFERROR(L148/L152,"NA") -> 0.566787 | M113: =IFERROR(M148/M152,"NA") -> 0.48529412 | N113: =IFERROR(N148/N152,"NA") -> 0.26689476 | O113: =IFERROR(O148/O152,"NA") -> 0.55430096 | P113: =IFERROR(P148/P152,"NA") -> 0.98808983 | Q113: =IFERROR(Q148/Q152,"NA") -> 1.6839997 | R113: =IFERROR(R148/R152,"NA") -> 2.1854594 | S113: =IFERROR(S148/S152,"NA") -> 3.7562931 | U113: =IFERROR(U148/U152,"NA") -> 3.7562931
C114: Financial Debt/Equity | G114: % | K114: =SUM(K150:K151)/K148 -> 0.78947368 | L114: =SUM(L150:L151)/L148 -> 0.76433121 | M114: =SUM(M150:M151)/M148 -> 1.0606061 | N114: =SUM(N150:N151)/N148 -> 2.7467951 | O114: =SUM(O150:O151)/O148 -> 0.8040741 | P114: =SUM(P150:P151)/P148 -> 0.012053737 | Q114: =SUM(Q150:Q151)/Q148 -> -0.40617568 | R114: =SUM(R150:R151)/R148 -> -0.54243029 | S114: =SUM(S150:S151)/S148 -> -0.73378009 | U114: =SUM(U150:U151)/U148 -> -0.73378009
C115: =Assumptions!C19 -> Interest Rate | G115: % | K115: =-IFERROR(K26/AVERAGE(J59:K59),0) -> 0.025 | L115: =-IFERROR(L26/AVERAGE(K59:L59),0) -> 0.025 | M115: =-IFERROR(M26/AVERAGE(L59:M59),0) -> 0.025 | N115: =Assumptions!G19 -> 0.025 | O115: =N115 -> 0.025 | P115: =O115 -> 0.025 | Q115: =P115 -> 0.025 | R115: =Q115 -> 0.025 | S115: =R115 -> 0.025
C117: Liquidity Ratios
C118: Cash Ratio | G118: x | K118: =IFERROR(K41/SUM(K$54:K$55),"NA") -> 1.1111111 | L118: =IFERROR(L41/SUM(L$54:L$55),"NA") -> 1.2162162 | M118: =IFERROR(M41/SUM(M$54:M$55),"NA") -> 1.7142857 | N118: =IFERROR(N41/SUM(N$54:N$55),"NA") -> 3.8131728 | O118: =IFERROR(O41/SUM(O$54:O$55),"NA") -> 5.129094 | P118: =IFERROR(P41/SUM(P$54:P$55),"NA") -> 6.8115025 | Q118: =IFERROR(Q41/SUM(Q$54:Q$55),"NA") -> 8.7912061 | R118: =IFERROR(R41/SUM(R$54:R$55),"NA") -> 9.3566173 | S118: =IFERROR(S41/SUM(S$54:S$55),"NA") -> 10.985821 | U118: =IFERROR(U41/SUM(U$54:U$55),"NA") -> 10.985821
C119: Quick Ratio | G119: x | K119: =IFERROR(SUM(K41:K42)/SUM(K$54:K$55),"NA") -> 3.3333333 | L119: =IFERROR(SUM(L41:L42)/SUM(L$54:L$55),"NA") -> 2.7027027 | M119: =IFERROR(SUM(M41:M42)/SUM(M$54:M$55),"NA") -> 3 | N119: =IFERROR(SUM(N41:N42)/SUM(N$54:N$55),"NA") -> 6.5623137 | O119: =IFERROR(SUM(O41:O42)/SUM(O$54:O$55),"NA") -> 7.5836841 | P119: =IFERROR(SUM(P41:P42)/SUM(P$54:P$55),"NA") -> 9.2655303 | Q119: =IFERROR(SUM(Q41:Q42)/SUM(Q$54:Q$55),"NA") -> 11.290425 | R119: =IFERROR(SUM(R41:R42)/SUM(R$54:R$55),"NA") -> 11.855836 | S119: =IFERROR(SUM(S41:S42)/SUM(S$54:S$55),"NA") -> 13.48504 | U119: =IFERROR(SUM(U41:U42)/SUM(U$54:U$55),"NA") -> 13.48504
C120: Current Ratio | G120: x | K120: =IFERROR(SUM(K41:K44)/K56,"NA") -> 5.1481481 | L120: =IFERROR(SUM(L41:L44)/L56,"NA") -> 4.2972973 | M120: =IFERROR(SUM(M41:M44)/M56,"NA") -> 4.0571429 | N120: =IFERROR(SUM(N41:N44)/N56,"NA") -> 7.4168383 | O120: =IFERROR(SUM(O41:O44)/O56,"NA") -> 8.4202902 | P120: =IFERROR(SUM(P41:P44)/P56,"NA") -> 10.102354 | Q120: =IFERROR(SUM(Q41:Q44)/Q56,"NA") -> 12.129746 | R120: =IFERROR(SUM(R41:R44)/R56,"NA") -> 12.695157 | S120: =IFERROR(SUM(S41:S44)/S56,"NA") -> 14.324361 | U120: =IFERROR(SUM(U41:U44)/U56,"NA") -> 14.324361
C122: Growth Rates
C123: Revenue growth | G123: % | K123: =IFERROR(K10/J10-1,"NA") -> NA | L123: =IFERROR(L10/K10-1,"NA") -> 0.055555556 | M123: =IFERROR(M10/L10-1,"NA") -> 0.052631579 | N123: =IFERROR(N10/L10-1,"NA") -> 0.108 | O123: =IFERROR(O10/M10-1,"NA") -> 0.131545 | P123: =IFERROR(P10/O10-1,"NA") -> 0.075 | Q123: =IFERROR(Q10/P10-1,"NA") -> 0.05 | R123: =IFERROR(R10/Q10-1,"NA") -> 0.05 | S123: =IFERROR(S10/R10-1,"NA") -> 0.05 | U123: =IFERROR((O10/P10)^(1/$U$7-$O$8)-1,"NA") -> 0.059562969
C124: Gross Profit Growth | G124: % | K124: =IFERROR(K14/J14-1,"NA") -> NA | L124: =IFERROR(L14/K14-1,"NA") -> -0.02 | M124: =IFERROR(M14/L14-1,"NA") -> 0.020408163 | N124: =IFERROR(N14/L14-1,"NA") -> 0.074081633 | O124: =IFERROR(O14/M14-1,"NA") -> -0.0042404 | P124: =IFERROR(P14/O14-1,"NA") -> 0.075 | Q124: =IFERROR(Q14/P14-1,"NA") -> 0.073863636 | R124: =IFERROR(R14/Q14-1,"NA") -> 0.05 | S124: =IFERROR(S14/R14-1,"NA") -> 0.05 | U124: =IFERROR((O14/P14)^(1/$U$7-$O$8)-1,"NA") -> 0.059562969
C125: EBITDA Growth | G125: % | K125: =IFERROR(K18/J18-1,"NA") -> NA | L125: =IFERROR(L18/K18-1,"NA") -> 0.099236641 | M125: =IFERROR(M18/L18-1,"NA") -> -0.36111111 | N125: =IFERROR(N18/L18-1,"NA") -> -0.11006944 | O125: =IFERROR(O18/M18-1,"NA") -> 0.19639639 | P125: =IFERROR(P18/O18-1,"NA") -> 0.075 | Q125: =IFERROR(Q18/P18-1,"NA") -> 0.066121495 | R125: =IFERROR(R18/Q18-1,"NA") -> -0.0011242604 | S125: =IFERROR(S18/R18-1,"NA") -> -0.019735205 | U125: =IFERROR((O18/P18)^(1/$U$7-$O$8)-1,"NA") -> 0.059562969
C126: EBIT Growth | G126: % | K126: =IFERROR(K22/J22-1,"NA") -> NA | L126: =IFERROR(L22/K22-1,"NA") -> 0.10743802 | M126: =IFERROR(M22/L22-1,"NA") -> -0.3880597 | N126: =IFERROR(N22/L22-1,"NA") -> -0.043656716 | O126: =IFERROR(O22/M22-1,"NA") -> -0.023555266 | P126: =IFERROR(P22/O22-1,"NA") -> 0.10310095 | Q126: =IFERROR(Q22/P22-1,"NA") -> 0.088580326 | R126: =IFERROR(R22/Q22-1,"NA") -> -0.0014750533 | S126: =IFERROR(S22/R22-1,"NA") -> -0.077982444 | U126: =IFERROR((O22/P22)^(1/$U$7-$O$8)-1,"NA") -> 0.081663579
C127: Net Income Growth | G127: % | K127: =IFERROR(K31/J31-1,"NA") -> NA | L127: =IFERROR(L31/K31-1,"NA") -> 0.10927505 | M127: =IFERROR(M31/L31-1,"NA") -> -0.40461317 | N127: =IFERROR(N31/L31-1,"NA") -> -0.053147525 | O127: =IFERROR(O31/M31-1,"NA") -> -0.025750209 | P127: =IFERROR(P31/O31-1,"NA") -> 0.11936269 | Q127: =IFERROR(Q31/P31-1,"NA") -> 0.10152606 | R127: =IFERROR(R31/Q31-1,"NA") -> 0.0065379733 | S127: =IFERROR(S31/R31-1,"NA") -> -0.071950312 | U127: =IFERROR((O31/P31)^(1/$U$7-$O$8)-1,"NA") -> 0.094401453
C128: Asset Growth | G128: % | K128: =IFERROR(K50/J50-1,"NA") -> NA | L128: =IFERROR(L50/K50-1,"NA") -> 0.09118541 | M128: =IFERROR(M50/L50-1,"NA") -> 0.022284123 | N128: =IFERROR(N50/L50-1,"NA") -> -0.25709354 | O128: =IFERROR(O50/M50-1,"NA") -> -0.23836195 | P128: =IFERROR(P50/O50-1,"NA") -> 0.056186764 | Q128: =IFERROR(Q50/P50-1,"NA") -> 0.066132759 | R128: =IFERROR(R50/Q50-1,"NA") -> 0.064197244 | S128: =IFERROR(S50/R50-1,"NA") -> 0.049922379 | U128: =IFERROR((O50/P50)^(1/$U$7-$O$8)-1,"NA") -> 0.044702362
C129: Equity Growth | G129: % | K129: =IFERROR(K62/J62-1,"NA") -> NA | L129: =IFERROR(L62/K62-1,"NA") -> 0.032894737 | M129: =IFERROR(M62/L62-1,"NA") -> -0.15923567 | N129: =IFERROR(N62/L62-1,"NA") -> -0.67535994 | O129: =IFERROR(O62/M62-1,"NA") -> -0.31381583 | P129: =IFERROR(P62/O62-1,"NA") -> 0.48948248 | Q129: =IFERROR(Q62/P62-1,"NA") -> 0.36198996 | R129: =IFERROR(R62/Q62-1,"NA") -> 0.26751786 | S129: =IFERROR(S62/R62-1,"NA") -> 0.1958709 | U129: =IFERROR((O62/P62)^(1/$U$7-$O$8)-1,"NA") -> 0.37539778
C131: Profitability
C132: NOPLAT | G132: =Assumptions!$G$14 -> USD | K132: =DCF!I18+DCF!I19 -> 0 | L132: =DCF!J18+DCF!J19 -> 0 | M132: =DCF!M18+DCF!M19 -> 0 | N132: =DCF!M18+DCF!M19 -> 0 | O132: =DCF!N18+DCF!N19 -> 600513.51 | P132: =DCF!O18+DCF!O19 -> 662427.02 | Q132: =DCF!P18+DCF!P19 -> 721105.03 | R132: =DCF!Q18+DCF!Q19 -> 720041.36 | S132: =DCF!R18+DCF!R19 -> 663890.77
C133: Revenue/Invested Capital | G133: x | K133: =IFERROR(K10/AVERAGE(J152:K152),0) -> 1.6544118 | L133: =IFERROR(L10/AVERAGE(K152:L152),0) -> 1.7304189 | M133: =IFERROR(M10/AVERAGE(L152:M152),0) -> 1.8214936 | N133: =IFERROR(N10/AVERAGE(L152:N152),0) -> 2.1337395 | O133: =IFERROR(O10/AVERAGE(M152:O152),0) -> 2.7097471 | P133: =IFERROR(P10/AVERAGE(O152:P152),0) -> 4.0554546 | Q133: =IFERROR(Q10/AVERAGE(P152:Q152),0) -> 5.1993448 | R133: =IFERROR(R10/AVERAGE(Q152:R152),0) -> 6.2178477 | S133: =IFERROR(S10/AVERAGE(R152:S152),0) -> 7.7919328
C134: ROIC | G134: % | K134: =IFERROR(K132/AVERAGE(J152:K152),"NA") -> 0 | L134: =IFERROR(L132/AVERAGE(K152:L152),"NA") -> 0 | M134: =IFERROR(M132/AVERAGE(L152:M152),"NA") -> 0 | N134: =IFERROR(N132/AVERAGE(L152:N152),"NA") -> 0 | O134: =IFERROR(O132/AVERAGE(M152:O152),"NA") -> 0.2876138 | P134: =IFERROR(P132/AVERAGE(O152:P152),"NA") -> 0.44169989 | Q134: =IFERROR(Q132/AVERAGE(P152:Q152),"NA") -> 0.58709387 | R134: =IFERROR(R132/AVERAGE(Q152:R152),"NA") -> 0.6676804 | S134: =IFERROR(S132/AVERAGE(R152:S152),"NA") -> 0.734723
C135: ROA | G135: % | K135: =IFERROR((K31-K26)/AVERAGE(J50:K50),"NA") -> 0.27868541 | L135: =IFERROR((L31-L26)/AVERAGE(K50:L50),"NA") -> 0.29501272 | M135: =IFERROR((M31-M26)/AVERAGE(L50:M50),"NA") -> 0.17256371 | N135: =IFERROR((N31-N26)/AVERAGE(L50:N50),"NA") -> 0.29423441 | O135: =IFERROR((O31-O26)/AVERAGE(M50:O50),"NA") -> 0.20107081 | P135: =IFERROR((P31-P26)/AVERAGE(O50:P50),"NA") -> 0.23388158 | Q135: =IFERROR((Q31-Q26)/AVERAGE(P50:Q50),"NA") -> 0.23899826 | R135: =IFERROR((R31-R26)/AVERAGE(Q50:R50),"NA") -> 0.22347867 | S135: =IFERROR((S31-S26)/AVERAGE(R50:S50),"NA") -> 0.19455833
...

Sheet DCF
B2: =Title!$B$5 -> DCF Valuation Model | S2: =Title!#REF!&" "&Title!#REF! -> #REF!
S3: =Title!#REF! -> #REF! | U3: =SUM(U4:U59) -> 0
C5: Free Cash Flow to Firm
C6: ="All amounts in "&Assumptions!$G$14 -> All amounts in USD
A7: 1 | C7: =C5 -> Free Cash Flow to Firm | M7: =Financials!M$7 -> 2026 | N7: =Financials!O$7 -> 2027 | O7: =Financials!P$7 -> 2028 | P7: =Financials!Q$7 -> 2029 | Q7: =Financials!R$7 -> 2030 | R7: =Financials!S$7 -> 2031
C8: Year | M8: =Financials!M$8 -> 0 | N8: =Financials!O$8 -> 1 | O8: =Financials!P$8 -> 2 | P8: =Financials!Q$8 -> 3 | Q8: =Financials!R$8 -> 4 | R8: =Financials!S$8 -> 5
C10: =Assumptions!C60 -> Discount Rate (WACC) | H10: =Assumptions!E60 -> % | M10: =Assumptions!G60 -> 0.099125
C11: =Assumptions!C59&" and Period" -> Discounting Method and Period | H11: =Assumptions!E59 -> Years | M11: =Assumptions!G59 -> Mid-Year
C12: =Assumptions!R82 -> Mid-Year | F12: =Assumptions!T82 -> 0.5
C13: =Assumptions!R83 -> End of Year | F13: =Assumptions!T83 -> 1
C15: ='Terminal Value'!C137 -> Selected Terminal Value Model | M15: ='Executive Summary'!$P$81 -> Two Stage Value Driver
C17: =C7 -> Free Cash Flow to Firm
C18: EBIT | H18: =Assumptions!$G$14 -> USD | N18: =Financials!O22 -> 800684.68 | O18: =Financials!P22 -> 883236.03 | P18: =Financials!Q22 -> 961473.37 | Q18: =Financials!R22 -> 960055.14 | R18: =Financials!S22 -> 885187.7 | U18: =SUM(N18:R18)-SUM(Financials!O22:S22) -> 0
C19: Adjusted Tax (1-t) | H19: =Assumptions!$G$14 -> USD | N19: =IF(N18<0,0,-N18*Financials!O145) -> -200171.17 | O19: =IF(O18<0,0,-O18*Financials!P145) -> -220809.01 | P19: =IF(P18<0,0,-P18*Financials!Q145) -> -240368.34 | Q19: =IF(Q18<0,0,-Q18*Financials!R145) -> -240013.79 | R19: =IF(R18<0,0,-R18*Financials!S145) -> -221296.92
C20: Addback Depreciation | H20: =Assumptions!$G$14 -> USD | N20: =Financials!O76 -> 300000 | O20: =Financials!P76 -> 300000 | P20: =Financials!Q76 -> 300000 | Q20: =Financials!R76 -> 300000 | R20: =Financials!S76 -> 350000
C21: Change in Net Working Capital | H21: =Assumptions!$G$14 -> USD | N21: =SUM(Financials!O77:O82) -> -24378.865 | O21: =SUM(Financials!P77:P82) -> -31316.427 | P21: =SUM(Financials!Q77:Q82) -> -25763.406 | Q21: =SUM(Financials!R77:R82) -> -24557.18 | R21: =SUM(Financials!S77:S82) -> -25785.039
C22: CAPEX | H22: =Assumptions!$G$14 -> USD | N22: =Financials!O86 -> 0 | O22: =Financials!P86 -> 0 | P22: =Financials!Q86 -> 0 | Q22: =Financials!R86 -> -250000 | R22: =Financials!S86 -> 0
C23: =C17 -> Free Cash Flow to Firm | H23: =Assumptions!$G$14 -> USD | N23: =SUM(N18:N22) -> 876134.65 | O23: =SUM(O18:O22) -> 931110.6 | P23: =SUM(P18:P22) -> 995341.62 | Q23: =SUM(Q18:Q22) -> 745484.18 | R23: =SUM(R18:R22) -> 988105.73 | U23: =SUM(N18:R22)-SUM(N23:R23) -> 0
C27: DCF Valuation
C28: ="All amounts in "&Assumptions!$G$14 -> All amounts in USD
A29: =A7+1 -> 2 | C29: =C27 -> DCF Valuation | H29: Unit | N29: =Financials!O$7 -> 2027 | O29: =Financials!P$7 -> 2028 | P29: =Financials!Q$7 -> 2029 | Q29: =Financials!R$7 -> 2030 | R29: =Financials!S$7 -> 2031
C30: Year | N30: =Financials!O$8 -> 1 | O30: =Financials!P$8 -> 2 | P30: =Financials!Q$8 -> 3 | Q30: =Financials!R$8 -> 4 | R30: =Financials!S$8 -> 5
C32: =C17 -> Free Cash Flow to Firm | H32: =Assumptions!$G$14 -> USD | N32: =N23 -> 876134.65 | O32: =O23 -> 931110.6 | P32: =P23 -> 995341.62 | Q32: =Q23 -> 745484.18 | R32: =R23 -> 988105.73
C33: Terminal Value (TV) | H33: =Assumptions!$G$14 -> USD | R33: ='Terminal Value'!H138 -> 4379465.1
C34: =C32&" incl. TV" -> Free Cash Flow to Firm incl. TV | H34: =Assumptions!$G$14 -> USD | N34: =SUM(N32:N33) -> 876134.65 | O34: =SUM(O32:O33) -> 931110.6 | P34: =SUM(P32:P33) -> 995341.62 | Q34: =SUM(Q32:Q33) -> 745484.18 | R34: =SUM(R32:R33) -> 5367570.8
C35: Discounting Period | H35: Years | N35: =IF(M11=C12,F12,IF(M11=C13,F13,0)) -> 0.5 | O35: =N35+1 -> 1.5 | P35: =O35+1 -> 2.5 | Q35: =P35+1 -> 3.5 | R35: =Q35+1 -> 4.5
C37: Discount Factor | H37: x | N37: =1/(1+$M$10)^N35 -> 0.95384203 | O37: =1/(1+$M$10)^O35 -> 0.86781943 | P37: =1/(1+$M$10)^P35 -> 0.78955481 | Q37: =1/(1+$M$10)^Q35 -> 0.71834852 | R37: =1/(1+$M$10)^R35 -> 0.65356399
C39: PV of Forecast Period | N39: =N32*N$37 -> 835694.05 | O39: =O32*O$37 -> 808035.87 | P39: =P32*P$37 -> 785876.77 | Q39: =Q32*Q$37 -> 535517.45 | R39: =R32*R$37 -> 645790.32
C40: PV of Terminal Value | R40: =R33*R$37 -> 2862260.7
C41: Discounted Cash Flows | H41: =Assumptions!$G$14 -> USD | N41: =SUM(N39:N40) -> 835694.05 | O41: =SUM(O39:O40) -> 808035.87 | P41: =SUM(P39:P40) -> 785876.77 | Q41: =SUM(Q39:Q40) -> 535517.45 | R41: =SUM(R39:R40) -> 3508051
C45: DCF Valuation Result | M45: =DATE(M7,12,31) -> 44925 | P45: Terminal Value Y5
C46: =C40 -> PV of Terminal Value | H46: =Assumptions!$G$14 -> USD | M46: =R40 -> 2862260.7 | N46: =IFERROR(M46/M$48,0) -> 0.4421726 | P46: Enterprise Value | Q46: =Assumptions!$G$14 -> USD | R46: =R33 -> 4379465.1
C47: =C39 -> PV of Forecast Period | H47: =Assumptions!$G$14 -> USD | M47: =M48-M46 -> 3610914.5 | N47: =IFERROR(M47/M$48,0) -> 0.5578274 | P47: ./. Financial Debt | Q47: =Assumptions!$G$14 -> USD | R47: =-Financials!$S$59 -> -500000
C48: Enterprise Value | H48: =Assumptions!$G$14 -> USD | M48: =SUM(N41:R41) -> 6473175.1 | N48: =SUM(N46:N47) -> 1 | P48: Cash | Q48: =Assumptions!$G$14 -> USD | R48: =+Financials!$S$41 -> 2543752.2
C49: Financial Debt | H49: =Assumptions!$G$14 -> USD | M49: =-Financials!M$59 -> -2000000 | N49: =IFERROR(M49/M$48,0) -> -0.30896739 | P49: Equity Value | Q49: =Assumptions!$G$14 -> USD | R49: =SUM(R46:R48) -> 6423217.3
C50: Cash | H50: =Assumptions!$G$14 -> USD | M50: =Financials!M$41 -> 600000 | N50: =IFERROR(M50/M$48,0) -> 0.092690216
C51: Equity Value | H51: =Assumptions!$G$14 -> USD | M51: =SUM(M48:M50) -> 5073175.1 | N51: =IFERROR(M51/M$48,0) -> 0.78372283
C53: Implied Multiples | M53: =M30 -> 0 | N53: =N30 -> 1 | R53: Terminal Value Y5
C54: =Assumptions!$C$95 -> EV/Revenue Exit Multiple | H54: =Assumptions!$E$95 -> x | M54: =IFERROR($M$48/Financials!M$10,"NA") -> 1.294635 | N54: =IFERROR($M$48/Financials!O$10,"NA") -> 1.1441304 | R54: =IFERROR($R$46/Financials!S10,0) -> 0.62201789
C55: =Assumptions!$C$96 -> EV/EBITDA Exit Multiple | H55: =Assumptions!$E$96 -> x | M55: =IFERROR($M$48/Financials!M$18,"NA") -> 7.0360599 | N55: =IFERROR($M$48/Financials!O$18,"NA") -> 5.8810441 | R55: =IFERROR($R$46/Financials!S18,0) -> 3.5455867
C56: =Assumptions!$C$97 -> EV/EBIT Exit Multiple | H56: =Assumptions!$E$97 -> x | M56: =IFERROR($M$48/Financials!M$22,"NA") -> 7.894116 | N56: =IFERROR($M$48/Financials!O$22,"NA") -> 8.0845497 | R56: =IFERROR($R$46/Financials!S22,0) -> 4.9474988
C57: =Assumptions!$C$98 -> P/E Exit Multiple | H57: =Assumptions!$E$98 -> x | M57: =IFERROR($M$51/Financials!M$31,"NA") -> 8.7350876 | N57: =IFERROR($M$51/Financials!O$31,"NA") -> 8.9659631 | R57: =IFERROR(($R$49)/Financials!S31,0) -> 9.8560458
C58: =Assumptions!$C$99 -> P/B Exit Multiple | H58: =Assumptions!$E$99 -> x | M58: =IFERROR($M$51/Financials!M$62,"NA") -> 3.8433145 | N58: =IFERROR($M$51/Financials!O$62,"NA") -> 5.6009955 | R58: =IFERROR(($R$49)/Financials!S62,0) -> 2.3061646
C63: =Title!#REF! -> #REF!
C64: =Title!#REF! -> #REF!

Sheet Terminal Value
B2: =Title!$B$5 -> DCF Valuation Model | U2: Check
U3: =SUM(U5:U846) -> 0
C5: Terminal Value Models
C6: ="All amounts in "&Assumptions!$G$14 -> All amounts in USD
A7: 1 | C7: =Assumptions!K67 -> Capitalized Earnings
C12: =Financials!C22&" (Year "&Financials!S8&")" -> EBIT (Year 5) | G12: =Assumptions!$G$14 -> USD | H12: =Financials!S22 -> 885187.7
C13: Tax Rate | G13: % | H13: =Financials!S145 -> 0.25
C14: =Financials!C30 -> Income Taxes | G14: =Assumptions!$G$14 -> USD | H14: =-H12*H13 -> -221296.92
C15: NOPLAT | G15: =Assumptions!$G$14 -> USD | H15: =H12+H14 -> 663890.77
C17: =Assumptions!C60 -> Discount Rate (WACC) | G17: =Assumptions!E60 -> % | H17: =Assumptions!G82 -> 0.099125
C18: ="TV "&C7 -> TV Capitalized Earnings | G18: =Assumptions!$G$14 -> USD | H18: =MAX(IFERROR(H15/H17,0),0) -> 6697511
C19: =HYPERLINK("#"&CELL("address",$C$138),"=> Compare "&$C$122) -> => Compare Terminal Value Models
C23: ="All amounts in "&Assumptions!$G$14 -> All amounts in USD
A24: =A7+1 -> 2 | C24: =Assumptions!K68 -> Gordon Growth
C29: TV | G29: Terminal Value
C30: FCF | G30: Free Cash Flows
C31: g | G31: Long-term Growth Rate
C32: WACC | G32: Weighted Average Cost of Capital (Discount Rate)
C34: =DCF!C$23&" (Year "&Financials!S8&")" -> Free Cash Flow to Firm (Year 5) | G34: =Assumptions!$G$14 -> USD | H34: =DCF!R$23 -> 988105.73
C35: =Assumptions!$C$60 -> Discount Rate (WACC) | G35: =Assumptions!$E$60 -> % | H35: =Assumptions!$G$60 -> 0.099125
C36: =Assumptions!$C$86 -> Growth Rate | G36: =Assumptions!$E$82 -> % | H36: =Assumptions!$G$86 -> 0.025
C37: ="TV "&C24 -> TV Gordon Growth | G37: =Assumptions!$G$14 -> USD | H37: =MAX(IFERROR((H$34*(1+$H$36)/($H$35-$H$36)),0),0) -> 13663519
C38: =HYPERLINK("#"&CELL("address",$C$138),"=> Compare "&$C$122) -> => Compare Terminal Value Models
C42: ="All amounts in "&Assumptions!$G$14 -> All amounts in USD
A43: =A24+1 -> 3 | C43: =Assumptions!K69 -> H-Model | L43: Growth Rates
L44: =F57 -> %
C49: TV | G49: Terminal Value
C50: FCF | G50: Free Cash Flows
C51: gL | G51: Long-term Growth Rate
C52: gH | G52: Growth rate during high growth period
C53: H | G53: Period of High Growth divided in half
C54: WACC | G54: Weighted Average Cost of Capital (Discount Rate)
C56: =DCF!C$23&" (Year "&Financials!S$8&")" -> Free Cash Flow to Firm (Year 5) | F56: =Assumptions!$G$14 -> USD | G56: =DCF!R$23 -> 988105.73 | L56: ="High Growth Period (Year "&G61&" - "&G62-1&")" -> High Growth Period (Year 6 - 15) | O56: =G58 -> 0.06
C57: Discount Rate | F57: =Assumptions!L94 -> % | G57: =Assumptions!M94 -> 0.099125 | L57: ="Low Growth Period (Year "&G62&" - Infinity)" -> Low Growth Period (Year 16 - Infinity) | O57: =G59 -> 0.03
C58: =Assumptions!C89 -> High Growth | F58: =Assumptions!E89 -> % | G58: =Assumptions!G89 -> 0.06
C59: =Assumptions!C90 -> Low Growth | F59: =Assumptions!E90 -> % | G59: =Assumptions!G90 -> 0.03
C60: =Assumptions!C91 -> Period of High Growth | F60: =Assumptions!E91 -> Years | G60: =Assumptions!G91 -> 10
C61: Start High Growth | F61: Year | G61: ='Two Stage Value Driver Model'!$R$8+1 -> 6
C62: Start Low Growth | F62: Year | G62: =G61+G60 -> 16
C64: ="TV "&C43 -> TV H-Model | G64: =(((G56*(1+G59))+(G56*(G60/2)*(G58-G59))))/(G57-G59) -> 16867483
C65: =HYPERLINK("#"&CELL("address",$C$138),"=> Compare "&$C$122) -> => Compare Terminal Value Models
C69: ="All amounts in "&Assumptions!$G$14 -> All amounts in USD
A70: =A43+1 -> 4 | C70: Exit Multiples
C72: Exit Valuation Method | I72: Exit Multiple | K72: ="Fundamentals (Year "&Financials!S$8&")" -> Fundamentals (Year 5) | O72: Terminal Value | P72: Debt | Q72: Cash | R72: TV - Equity Value
C74: =Assumptions!C95 -> EV/Revenue Exit Multiple | G74: x | I74: =Assumptions!G95 -> 2.5 | K74: =Financials!C10 -> Revenue | L74: =Assumptions!$G$14 -> USD | M74: =Financials!S10 -> 7040738.2 | O74: =I74*M74 -> 17601845 | P74: =-Financials!S150 -> -500000 | Q74: =-Financials!S151 -> 2543752.2 | R74: =SUM(O74:Q74) -> 19645598 | U74: =SUM(O74:Q74)-R74 -> 0
C75: =Assumptions!C96 -> EV/EBITDA Exit Multiple | G75: x | I75: =Assumptions!G96 -> 6 | K75: =Financials!C18 -> EBITDA | L75: =Assumptions!$G$14 -> USD | M75: =Financials!S18 -> 1235187.7 | O75: =I75*M75 -> 7411126.2 | P75: =P74 -> -500000 | Q75: =Q74 -> 2543752.2 | R75: =SUM(O75:Q75) -> 9454878.4 | U75: =SUM(O75:Q75)-R75 -> 0
C76: =Assumptions!C97 -> EV/EBIT Exit Multiple | G76: x | I76: =Assumptions!G97 -> 7 | K76: =Financials!C22 -> EBIT | L76: =Assumptions!$G$14 -> USD | M76: =Financials!S22 -> 885187.7 | O76: =I76*M76 -> 6196313.9 | P76: =P75 -> -500000 | Q76: =Q75 -> 2543752.2 | R76: =SUM(O76:Q76) -> 8240066.1 | U76: =SUM(O76:Q76)-R76 -> 0
C77: =Assumptions!C98 -> P/E Exit Multiple | G77: x | I77: =Assumptions!G98 -> 5 | K77: =Financials!C31 -> Net Income/Loss | L77: =Assumptions!$G$14 -> USD | M77: =Financials!S31 -> 651703.27 | O77: =R77-Q77-P77 -> 1214764.1 | P77: =P76 -> -500000 | Q77: =Q76 -> 2543752.2 | R77: =I77*M77 -> 3258516.4 | U77: =SUM(O77:Q77)-R77 -> 0
C78: =Assumptions!C99 -> P/B Exit Multiple | G78: x | I78: =Assumptions!G99 -> 2 | K78: =Financials!C62 -> Shareholder's Equity | L78: =Assumptions!$G$14 -> USD | M78: =Financials!S62 -> 2785238 | O78: =R78-Q78-P78 -> 3526723.8 | P78: =P77 -> -500000 | Q78: =Q77 -> 2543752.2 | R78: =I78*M78 -> 5570476.1 | U78: =SUM(O78:Q78)-R78 -> 0
C79: =HYPERLINK("#"&CELL("address",$C$138),"=> Compare "&$C$122) -> => Compare Terminal Value Models
C83: ="All amounts in "&Assumptions!$G$14 -> All amounts in USD
A84: =A70+1 -> 5 | C84: =Assumptions!K75 -> One Stage Value Driver | L84: ROIC vs. WACC
L86: =C96&" %" -> ROIC % | S86: =C97&" %" -> WACC %
M87: Year | N87: =Financials!C134 -> ROIC | O87: WACC | P87: Excess Return
N89: % | O89: % | P89: %
M91: =Financials!O8 -> 1 | N91: =Financials!O134 -> 0.2876138 | O91: =$G$100 -> 0.099125 | P91: =N91-O91 -> 0.1884888
C92: Invested Capital | G92: Sources of funding made by shareholders and debt financing | M92: =Financials!P8 -> 2 | N92: =Financials!P134 -> 0.44169989 | O92: =$G$100 -> 0.099125 | P92: =N92-O92 -> 0.34257489
C93: TV | G93: Terminal Value | M93: =Financials!Q8 -> 3 | N93: =Financials!Q134 -> 0.58709387 | O93: =$G$100 -> 0.099125 | P93: =N93-O93 -> 0.48796887
C94: NOPLAT | G94: Net Operating Profit less Adjusted Taxes | M94: =Financials!R8 -> 4 | N94: =Financials!R134 -> 0.6676804 | O94: =$G$100 -> 0.099125 | P94: =N94-O94 -> 0.5685554
C95: g | G95: Growth Rate | M95: =Financials!S8 -> 5 | N95: =Financials!S134 -> 0.734723 | O95: =$G$100 -> 0.099125 | P95: =N95-O95 -> 0.635598
C96: ROIC | G96: Return on Invested Capital | M96: Terminal Value | N96: =G102 -> 0.119125 | O96: =$G$100 -> 0.099125 | P96: =N96-O96 -> 0.02
C97: WACC | G97: Weighted Average Cost of Capital (Discount Rate)
C99: Assumptions
C100: =Assumptions!K82 -> Discount Rate | F100: =Assumptions!$E$60 -> % | G100: =Assumptions!M82 -> 0.099125
C101: =Assumptions!K83 -> Spread to Discount Rate | F101: =Assumptions!$E$60 -> % | G101: =Assumptions!M83 -> 0.02
C102: =C96 -> ROIC | F102: =Assumptions!$E$82 -> % | G102: =G100+G101 -> 0.119125
C103: =Financials!C152&" (Year "&Financials!S$8&")" -> Invested Capital (Year 5) | F103: =Assumptions!$G$14 -> USD | G103: ='Two Stage Value Driver Model'!R34 -> 741485.81
C104: ="NOPLAT (Year "&Financials!S$8&")" -> NOPLAT (Year 5) | F104: =Assumptions!$G$14 -> USD | G104: =G103*G102 -> 88329.498
C105: =Assumptions!$C$86 -> Growth Rate | F105: =Assumptions!$E$82 -> % | G105: =Assumptions!M85 -> 0.025
C106: ="TV "&C84 -> TV One Stage Value Driver | F106: =Assumptions!$G$14 -> USD | G106: =MAX(IFERROR((G$104*(1+G105)*(1-($G$105/G102))/($G$100-$G$105)),0),0) -> 965088.18
C107: =HYPERLINK("#"&CELL("address",$C$138),"=> Compare "&$C$122) -> => Compare Terminal Value Models
C110: ="All amounts in "&Assumptions!$G$14 -> All amounts in USD
A111: =A84+1 -> 6 | C111: =Assumptions!K76 -> Two Stage Value Driver | L111: ROCE vs. WACC
C113: ="TV "&C111 -> TV Two Stage Value Driver | F113: ='Two Stage Value Driver Model'!G78 -> USD | G113: ='Two Stage Value Driver Model'!H78 -> 4379465.1
C114: =HYPERLINK("#"&CELL("address",'Two Stage Value Driver Model'!$R$47),"=> Calculation of "&'Two Stage Value Driver Model'!$C$7) -> => Calculation of Two Stage Value Driver
C115: =HYPERLINK("#"&CELL("address",$C$138),"=> Compare "&$C$122) -> => Compare Terminal Value Models
C119: ="All amounts in "&Assumptions!$G$14 -> All amounts in USD
A120: =A111+1 -> 7 | C120: =C5&" Summary" -> Terminal Value Models Summary | L120: Overview - Terminal Value Results
L121: =Assumptions!$G$14 -> USD
C122: Terminal Value Models | H122: TV | I122: Factor (Y5) | J122: PV of TV
H123: Year 5 | J123: Year 0
H124: =Assumptions!$G$14 -> USD | I124: x | J124: =Assumptions!$G$14 -> USD
C126: =HYPERLINK("#"&CELL("address",'Terminal Value'!$H$18),'Terminal Value'!$C$7) -> Capitalized Earnings | G126: =Assumptions!$G$14 -> USD | H126: =H18 -> 6697511 | I126: =I$138 -> 0.65356399 | J126: =H126*$I$138 -> 4377251.9
C127: =HYPERLINK("#"&CELL("address",'Terminal Value'!$H$37),'Terminal Value'!$C$24) -> Gordon Growth | G127: =Assumptions!$G$14 -> USD | H127: =H37 -> 13663519 | I127: =I$138 -> 0.65356399 | J127: =H127*$I$138 -> 8929984.2
C128: =HYPERLINK("#"&CELL("address",'Terminal Value'!$G$64),'Terminal Value'!$C$43) -> H-Model | G128: =Assumptions!$G$14 -> USD | H128: =G64 -> 16867483 | I128: =I$138 -> 0.65356399 | J128: =H128*$I$138 -> 11023979
C129: =HYPERLINK("#"&CELL("address",'Terminal Value'!$O$74),Assumptions!K70) -> EV/Revenue Exit Multiple (2.5x) | G129: =Assumptions!$G$14 -> USD | H129: =O74 -> 17601845 | I129: =I$138 -> 0.65356399 | J129: =H129*$I$138 -> 11503932
C130: =HYPERLINK("#"&CELL("address",'Terminal Value'!$O$75),Assumptions!K71) -> EV/EBITDA Exit Multiple (6.0x) | G130: =Assumptions!$G$14 -> USD | H130: =O75 -> 7411126.2 | I130: =I$138 -> 0.65356399 | J130: =H130*$I$138 -> 4843645.2
C131: =HYPERLINK("#"&CELL("address",'Terminal Value'!$O$76),Assumptions!K72) -> EV/EBIT Exit Multiple (7.0x) | G131: =Assumptions!$G$14 -> USD | H131: =O76 -> 6196313.9 | I131: =I$138 -> 0.65356399 | J131: =H131*$I$138 -> 4049687.6
C132: =HYPERLINK("#"&CELL("address",'Terminal Value'!$O$77),Assumptions!K73) -> P/E Exit Multiple (5.0x) | G132: =Assumptions!$G$14 -> USD | H132: =O77 -> 1214764.1 | I132: =I$138 -> 0.65356399 | J132: =H132*$I$138 -> 793926.1
C133: =HYPERLINK("#"&CELL("address",'Terminal Value'!$O$78),Assumptions!K74) -> P/B Exit Multiple (2.0x) | G133: =Assumptions!$G$14 -> USD | H133: =O78 -> 3526723.8 | I133: =I$138 -> 0.65356399 | J133: =H133*$I$138 -> 2304939.7
C134: =HYPERLINK("#"&CELL("address",'Terminal Value'!$G$106),'Terminal Value'!$C$84) -> One Stage Value Driver | G134: =Assumptions!$G$14 -> USD | H134: =G106 -> 965088.18 | I134: =I$138 -> 0.65356399 | J134: =H134*$I$138 -> 630746.87
C135: =HYPERLINK("#"&CELL("address",'Two Stage Value Driver Model'!$R$47),'Two Stage Value Driver Model'!$C$7) -> Two Stage Value Driver | G135: =Assumptions!$G$14 -> USD | H135: ='Two Stage Value Driver Model'!R47 -> 4379465.1 | I135: =I$138 -> 0.65356399 | J135: =H135*$I$138 -> 2862260.7
C137: Selected Terminal Value Model
C138: ='Executive Summary'!$P$81 -> Two Stage Value Driver | G138: =Assumptions!$G$14 -> USD | H138: =IFERROR(INDEX('Terminal Value'!H126:H136,MATCH('Terminal Value'!C138,'Terminal Value'!C126:C136,0)),0) -> 4379465.1 | I138: =DCF!R37 -> 0.65356399 | J138: =H138*I138 -> 2862260.7

Sheet Two Stage Value Driver Model
B2: =Title!$B$5 -> DCF Valuation Model | AY2: Check
AY3: =SUM(AY5:AY794) -> 0
C5: =C7 -> Two Stage Value Driver
C6: ="All amounts in "&Assumptions!$G$14 -> All amounts in USD
A7: 1 | C7: =Assumptions!K76 -> Two Stage Value Driver | M7: =Financials!M$7 -> 2026 | N7: =Financials!O$7 -> 2027 | O7: =Financials!P$7 -> 2028 | P7: =Financials!Q$7 -> 2029 | Q7: =Financials!R$7 -> 2030 | R7: =Financials!S$7 -> 2031 | S7: =R7+1 -> 2032 | T7: =S7+1 -> 2033 | U7: =T7+1 -> 2034 | V7: =U7+1 -> 2035 | W7: =V7+1 -> 2036 | X7: =W7+1 -> 2037 | Y7: =X7+1 -> 2038 | Z7: =Y7+1 -> 2039 | ... AV7: =AU7+1 -> 2061
C8: Year | M8: =Financials!M$8 -> 0 | N8: =Financials!O$8 -> 1 | O8: =Financials!P$8 -> 2 | P8: =Financials!Q$8 -> 3 | Q8: =Financials!R$8 -> 4 | R8: =Financials!S$8 -> 5 | S8: =R8+1 -> 6 | T8: =S8+1 -> 7 | U8: =T8+1 -> 8 | V8: =U8+1 -> 9 | W8: =V8+1 -> 10 | X8: =W8+1 -> 11 | Y8: =X8+1 -> 12 | Z8: =Y8+1 -> 13 | ... AV8: =AU8+1 -> 35
C9: Terminal Value Year | S9: 1 | T9: =S9+1 -> 2 | U9: =T9+1 -> 3 | V9: =U9+1 -> 4 | W9: =V9+1 -> 5 | X9: =W9+1 -> 6 | Y9: =X9+1 -> 7 | Z9: =Y9+1 -> 8 | AA9: =Z9+1 -> 9 | ... AV9: =AU9+1 -> 30
C11: =Assumptions!R85 -> ROCE Stage I
C12: =Assumptions!$K$99 -> ROIC | D12: =Assumptions!R86 -> Steady Decline | G12: Annual Decline: | I12: =($I$60-$J$60)/($I$54) -> 0.0423732 | J12: % | N12: =N$15 -> 0.2876138 | O12: =O$15 -> 0.44169989 | P12: =P$15 -> 0.58709387 | Q12: =Q$15 -> 0.6676804 | R12: =R$15 -> 0.734723 | S12: =IF(S$9<$I$54,I60-$I12,$J$60) -> 0.6923498 | T12: =IF(T$9<$I$54,S12-$I12,$J$60) -> 0.6499766 | U12: =IF(U$9<$I$54,T12-$I12,$J$60) -> 0.6076034 | V12: =IF(V$9<$I$54,U12-$I12,$J$60) -> 0.5652302 | W12: =IF(W$9<$I$54,V12-$I12,$J$60) -> 0.522857 | X12: =IF(X$9<$I$54,W12-$I12,$J$60) -> 0.4804838 | Y12: =IF(Y$9<$I$54,X12-$I12,$J$60) -> 0.4381106 | Z12: =IF(Z$9<$I$54,Y12-$I12,$J$60) -> 0.3957374 | AA12: =IF(AA$9<$I$54,Z12-$I12,$J$60) -> 0.3533642 | ... AV12: =IF(AV$9<$I$54,AU12-$I12,$J$60) -> 0.099125
C13: =Assumptions!$K$99 -> ROIC | D13: =Assumptions!R87 -> Exponential Decline | G13: Curve: (X-X1)² = Y | I13: =($I$60-$J$60)/(($I$54)^2) -> 0.00282488 | J13: % | N13: =N$15 -> 0.2876138 | O13: =O$15 -> 0.44169989 | P13: =P$15 -> 0.58709387 | Q13: =Q$15 -> 0.6676804 | R13: =R$15 -> 0.734723 | S13: =IF(S$9<$I$54,$I$60-$I13*(S9^2),$J$60) -> 0.73189812 | T13: =IF(T$9<$I$54,$I$60-$I13*(T9^2),$J$60) -> 0.72342348 | U13: =IF(U$9<$I$54,$I$60-$I13*(U9^2),$J$60) -> 0.70929908 | V13: =IF(V$9<$I$54,$I$60-$I13*(V9^2),$J$60) -> 0.68952492 | W13: =IF(W$9<$I$54,$I$60-$I13*(W9^2),$J$60) -> 0.664101 | X13: =IF(X$9<$I$54,$I$60-$I13*(X9^2),$J$60) -> 0.63302732 | Y13: =IF(Y$9<$I$54,$I$60-$I13*(Y9^2),$J$60) -> 0.59630388 | Z13: =IF(Z$9<$I$54,$I$60-$I13*(Z9^2),$J$60) -> 0.55393068 | ... AV13: =IF(AV$9<$I$54,$I$60-$I13*(AV9^2),$J$60) -> 0.099125
C14: =Assumptions!$K$99 -> ROIC | D14: =Assumptions!R88 -> Decline Jump at End | N14: =N$15 -> 0.2876138 | O14: =O$15 -> 0.44169989 | P14: =P$15 -> 0.58709387 | Q14: =Q$15 -> 0.6676804 | R14: =R$15 -> 0.734723 | S14: =IF(S$9<$I$54,$I$60,$J$60) -> 0.734723 | T14: =IF(T$9<$I$54,$I$60,$J$60) -> 0.734723 | U14: =IF(U$9<$I$54,$I$60,$J$60) -> 0.734723 | V14: =IF(V$9<$I$54,$I$60,$J$60) -> 0.734723 | W14: =IF(W$9<$I$54,$I$60,$J$60) -> 0.734723 | X14: =IF(X$9<$I$54,$I$60,$J$60) -> 0.734723 | Y14: =IF(Y$9<$I$54,$I$60,$J$60) -> 0.734723 | Z14: =IF(Z$9<$I$54,$I$60,$J$60) -> 0.734723 | ... AV14: =IF(AV$9<$I$54,$I$60,$J$60) -> 0.099125
C15: =Assumptions!$K$99 -> ROIC | D15: ="Selected "&Assumptions!K100 -> Selected ROIC Curve | H15: Exponential Decline | N15: =Financials!O134 -> 0.2876138 | O15: =Financials!P134 -> 0.44169989 | P15: =Financials!Q134 -> 0.58709387 | Q15: =Financials!R134 -> 0.6676804 | R15: =Financials!S134 -> 0.734723 | S15: =IFERROR(INDEX(S$12:S$14,MATCH($H$15,$D$12:$D$14,0)),0) -> 0.73189812 | T15: =IFERROR(INDEX(T$12:T$14,MATCH($H$15,$D$12:$D$14,0)),0) -> 0.72342348 | U15: =IFERROR(INDEX(U$12:U$14,MATCH($H$15,$D$12:$D$14,0)),0) -> 0.70929908 | V15: =IFERROR(INDEX(V$12:V$14,MATCH($H$15,$D$12:$D$14,0)),0) -> 0.68952492 | W15: =IFERROR(INDEX(W$12:W$14,MATCH($H$15,$D$12:$D$14,0)),0) -> 0.664101 | X15: =IFERROR(INDEX(X$12:X$14,MATCH($H$15,$D$12:$D$14,0)),0) -> 0.63302732 | Y15: =IFERROR(INDEX(Y$12:Y$14,MATCH($H$15,$D$12:$D$14,0)),0) -> 0.59630388 | Z15: =IFERROR(INDEX(Z$12:Z$14,MATCH($H$15,$D$12:$D$14,0)),0) -> 0.55393068 | ... AV15: =IFERROR(INDEX(AV$12:AV$14,MATCH($H$15,$D$12:$D$14,0)),0) -> 0.099125
C17: Financial Forecast
C18: =Financials!C10 -> Revenue | J18: =Financials!G10 -> USD | N18: =Financials!O10 -> 5657725 | O18: =Financials!P10 -> 6082054.4 | P18: =Financials!Q10 -> 6386157.1 | Q18: =Financials!R10 -> 6705464.9 | R18: =Financials!S10 -> 7040738.2 | S18: =R18*(1+S$19) -> 7216756.7 | T18: =S18*(1+T$19) -> 7397175.6 | U18: =T18*(1+U$19) -> 7582105 | V18: =U18*(1+V$19) -> 7771657.6 | W18: =V18*(1+W$19) -> 7965949 | X18: =W18*(1+X$19) -> 8165097.7 | Y18: =X18*(1+Y$19) -> 8369225.2 | Z18: =Y18*(1+Z$19) -> 8578455.8 | ... AV18: =AU18*(1+AV$19) -> 14768424
C19: =Financials!C11 -> Revenue Growth | J19: =Financials!G11 -> % | N19: =Financials!O11 -> 0.075 | O19: =Financials!P11 -> 0.075 | P19: =Financials!Q11 -> 0.05 | Q19: =Financials!R11 -> 0.05 | R19: =Financials!S11 -> 0.05 | S19: =IF(S$9<=$I$54,$I$58,$J$58) -> 0.025 | T19: =IF(T$9<=$I$54,$I$58,$J$58) -> 0.025 | U19: =IF(U$9<=$I$54,$I$58,$J$58) -> 0.025 | V19: =IF(V$9<=$I$54,$I$58,$J$58) -> 0.025 | W19: =IF(W$9<=$I$54,$I$58,$J$58) -> 0.025 | X19: =IF(X$9<=$I$54,$I$58,$J$58) -> 0.025 | Y19: =IF(Y$9<=$I$54,$I$58,$J$58) -> 0.025 | Z19: =IF(Z$9<=$I$54,$I$58,$J$58) -> 0.025 | ... AV19: =IF(AV$9<=$I$54,$I$58,$J$58) -> 0.025
C21: =Financials!C18 -> EBITDA | J21: =Financials!G18 -> USD | N21: =Financials!O18 -> 1100684.7 | O21: =Financials!P18 -> 1183236 | P21: =Financials!Q18 -> 1261473.4 | Q21: =Financials!R18 -> 1260055.1 | R21: =Financials!S18 -> 1235187.7 | S21: =S25-S24 -> 1172459.2 | T21: =T25-T24 -> 1272249.3 | U21: =U25-U24 -> 1285953.6 | V21: =V25-V24 -> 1292126.2 | W21: =W25-W24 -> 1290196.4 | X21: =X25-X24 -> 1279565 | Y21: =Y25-Y24 -> 1259603.2 | Z21: =Z25-Z24 -> 1229651.3 | ... AV21: =AV25-AV24 -> 981595.58
C22: =C21&" Margin" -> EBITDA Margin | J22: =Financials!G14 -> USD | N22: =Financials!O19 -> 0.19454545 | O22: =Financials!P19 -> 0.19454545 | P22: =Financials!Q19 -> 0.19753247 | Q22: =Financials!R19 -> 0.18791466 | R22: =Financials!S19 -> 0.1754344 | S22: =IFERROR(S21/S18,0) -> 0.16246345 | T22: =IFERROR(T21/T18,0) -> 0.17199122 | U22: =IFERROR(U21/U18,0) -> 0.16960377 | V22: =IFERROR(V21/V18,0) -> 0.16626134 | W22: =IFERROR(W21/W18,0) -> 0.16196392 | X22: =IFERROR(X21/X18,0) -> 0.15671153 | Y22: =IFERROR(Y21/Y18,0) -> 0.15050415 | Z22: =IFERROR(Z21/Z18,0) -> 0.1433418 | ... AV22: =IFERROR(AV21/AV18,0) -> 0.066465831
C24: =Financials!C21 -> Depreciation | J24: =Financials!G21 -> USD | N24: =Financials!O21 -> -300000 | O24: =Financials!P21 -> -300000 | P24: =Financials!Q21 -> -300000 | Q24: =Financials!R21 -> -300000 | R24: =Financials!S21 -> -350000 | S24: =R24*(1+S$19) -> -358750 | T24: =S24*(1+T$19) -> -367718.75 | U24: =T24*(1+U$19) -> -376911.72 | V24: =U24*(1+V$19) -> -386334.51 | W24: =V24*(1+W$19) -> -395992.87 | X24: =W24*(1+X$19) -> -405892.7 | Y24: =X24*(1+Y$19) -> -416040.01 | Z24: =Y24*(1+Z$19) -> -426441.01 | ... AV24: =AU24*(1+AV$19) -> -734148.65
C25: =Financials!C22 -> EBIT | J25: =Financials!G22 -> USD | N25: =N21+N24 -> 800684.68 | O25: =O21+O24 -> 883236.03 | P25: =P21+P24 -> 961473.37 | Q25: =Q21+Q24 -> 960055.14 | R25: =R21+R24 -> 885187.7 | S25: =IFERROR(S28/(1-S26),0) -> 813709.17 | T25: =IFERROR(T28/(1-T26),0) -> 904530.53 | U25: =IFERROR(U28/(1-U26),0) -> 909041.88 | V25: =IFERROR(V28/(1-V26),0) -> 905791.68 | W25: =IFERROR(W28/(1-W26),0) -> 894203.49 | X25: =IFERROR(X28/(1-X26),0) -> 873672.26 | Y25: =IFERROR(Y28/(1-Y26),0) -> 843563.14 | Z25: =IFERROR(Z28/(1-Z26),0) -> 803210.25 | ... AV25: =IFERROR(AV28/(1-AV26),0) -> 247446.93
C26: =Financials!C145 -> Income Tax Rate | J26: =Financials!G145 -> % | N26: =Financials!O145 -> 0.25 | O26: =Financials!P145 -> 0.25 | P26: =Financials!Q145 -> 0.25 | Q26: =Financials!R145 -> 0.25 | R26: =Financials!S145 -> 0.25 | S26: =R26 -> 0.25 | T26: =S26 -> 0.25 | U26: =T26 -> 0.25 | V26: =U26 -> 0.25 | W26: =V26 -> 0.25 | X26: =W26 -> 0.25 | Y26: =X26 -> 0.25 | Z26: =Y26 -> 0.25 | ... AV26: =AU26 -> 0.25
C27: Pro Forma Taxes | J27: =Assumptions!$G$14 -> USD | N27: =N28-N25 -> -200171.17 | O27: =O28-O25 -> -220809.01 | P27: =P28-P25 -> -240368.34 | Q27: =Q28-Q25 -> -240013.79 | R27: =R28-R25 -> -221296.92 | S27: =-S25*S26 -> -203427.29 | T27: =-T25*T26 -> -226132.63 | U27: =-U25*U26 -> -227260.47 | V27: =-V25*V26 -> -226447.92 | W27: =-W25*W26 -> -223550.87 | X27: =-X25*X26 -> -218418.06 | Y27: =-Y25*Y26 -> -210890.78 | Z27: =-Z25*Z26 -> -200802.56 | ... AV27: =-AV25*AV26 -> -61861.732
C28: NOPLAT | J28: NOPLAT | N28: =N25*(1-N26) -> 600513.51 | O28: =O25*(1-O26) -> 662427.02 | P28: =P25*(1-P26) -> 721105.03 | Q28: =Q25*(1-Q26) -> 720041.36 | R28: =R25*(1-R26) -> 663890.77 | S28: =AVERAGE(R34:S34)*S15 -> 610281.88 | T28: =AVERAGE(S34:T34)*T15 -> 678397.9 | U28: =AVERAGE(T34:U34)*U15 -> 681781.41 | V28: =AVERAGE(U34:V34)*V15 -> 679343.76 | W28: =AVERAGE(V34:W34)*W15 -> 670652.62 | X28: =AVERAGE(W34:X34)*X15 -> 655254.19 | Y28: =AVERAGE(X34:Y34)*Y15 -> 632672.35 | Z28: =AVERAGE(Y34:Z34)*Z15 -> 602407.69 | ... AV28: =AVERAGE(AU34:AV34)*AV15 -> 185585.2
C29: Net Investment | J29: =Assumptions!$G$14 -> USD | N29: =N30-N28 -> 275621.14 | O29: =O30-O28 -> 268683.57 | P29: =P30-P28 -> 274236.59 | Q29: =Q30-Q28 -> 25442.82 | R29: =R30-R28 -> 324214.96 | S29: =R34-S34 -> -184697.31 | T29: =S34-T34 -> -23154.578 | U29: =T34-U34 -> -23733.443 | V29: =U34-V34 -> -24326.779 | W29: =V34-W34 -> -24934.948 | X29: =W34-X34 -> -25558.322 | Y29: =X34-Y34 -> -26197.28 | Z29: =Y34-Z34 -> -26852.212 | ... AV29: =AU34-AV34 -> -46228
C30: Free Cash Flow to Firm | J30: =Assumptions!$G$14 -> USD | N30: =DCF!N32 -> 876134.65 | O30: =DCF!O32 -> 931110.6 | P30: =DCF!P32 -> 995341.62 | Q30: =DCF!Q32 -> 745484.18 | R30: =DCF!R32 -> 988105.73 | S30: =SUM(S28:S29) -> 425584.57 | T30: =SUM(T28:T29) -> 655243.32 | U30: =SUM(U28:U29) -> 658047.97 | V30: =SUM(V28:V29) -> 655016.98 | W30: =SUM(W28:W29) -> 645717.67 | X30: =SUM(X28:X29) -> 629695.87 | Y30: =SUM(Y28:Y29) -> 606475.07 | Z30: =SUM(Z28:Z29) -> 575555.48 | ... AV30: =SUM(AV28:AV29) -> 139357.2
C32: =Financials!C86 -> Capital Expenditures | J32: =Assumptions!$G$14 -> USD | N32: =Financials!O86 -> 0 | O32: =Financials!P86 -> 0 | P32: =Financials!Q86 -> 0 | Q32: =Financials!R86 -> -250000 | R32: =Financials!S86 -> 0
C34: Invested Capital | J34: =Assumptions!$G$14 -> USD | N34: =Financials!O152 -> 1634063.8 | O34: =Financials!P152 -> 1365380.2 | P34: =Financials!Q152 -> 1091143.6 | Q34: =Financials!R152 -> 1065700.8 | R34: =Financials!S152 -> 741485.81 | S34: =IFERROR(S18/S35,0) -> 926183.13 | T34: =IFERROR(T18/T35,0) -> 949337.71 | U34: =IFERROR(U18/U35,0) -> 973071.15 | V34: =IFERROR(V18/V35,0) -> 997397.93 | W34: =IFERROR(W18/W35,0) -> 1022332.9 | X34: =IFERROR(X18/X35,0) -> 1047891.2 | Y34: =IFERROR(Y18/Y35,0) -> 1074088.5 | Z34: =IFERROR(Z18/Z35,0) -> 1100940.7 | ... AV34: =IFERROR(AV18/AV35,0) -> 1895348
C35: =Financials!C133 -> Revenue/Invested Capital | J35: x | N35: =Financials!O133 -> 2.7097471 | O35: =Financials!P133 -> 4.0554546 | P35: =Financials!Q133 -> 5.1993448 | Q35: =Financials!R133 -> 6.2178477 | R35: =Financials!S133 -> 7.7919328 | S35: =R35 -> 7.7919328 | T35: =S35 -> 7.7919328 | U35: =T35 -> 7.7919328 | V35: =U35 -> 7.7919328 | W35: =V35 -> 7.7919328 | X35: =W35 -> 7.7919328 | Y35: =X35 -> 7.7919328 | Z35: =Y35 -> 7.7919328 | ... AV35: =AU35 -> 7.7919328
C37: Terminal Value Calculation
C38: FCF Competitive Advantage Period | J38: =Assumptions!$G$14 -> USD | S38: =IF(S$9<=$I$54,S30,0) -> 425584.57 | T38: =IF(T$9<=$I$54,T30,0) -> 655243.32 | U38: =IF(U$9<=$I$54,U30,0) -> 658047.97 | V38: =IF(V$9<=$I$54,V30,0) -> 655016.98 | W38: =IF(W$9<=$I$54,W30,0) -> 645717.67 | X38: =IF(X$9<=$I$54,X30,0) -> 629695.87 | Y38: =IF(Y$9<=$I$54,Y30,0) -> 606475.07 | Z38: =IF(Z$9<=$I$54,Z30,0) -> 575555.48 | ... AV38: =IF(AV$9<=$I$54,AV30,0) -> 0
C39: TV end of Competitive Advantage Period | J39: =Assumptions!$G$14 -> USD | S39: =IF(S$9=$I$54,S30/($J$57-$J$58),0) -> 0 | T39: =IF(T$9=$I$54,T30/($J$57-$J$58),0) -> 0 | U39: =IF(U$9=$I$54,U30/($J$57-$J$58),0) -> 0 | V39: =IF(V$9=$I$54,V30/($J$57-$J$58),0) -> 0 | W39: =IF(W$9=$I$54,W30/($J$57-$J$58),0) -> 0 | X39: =IF(X$9=$I$54,X30/($J$57-$J$58),0) -> 0 | Y39: =IF(Y$9=$I$54,Y30/($J$57-$J$58),0) -> 0 | Z39: =IF(Z$9=$I$54,Z30/($J$57-$J$58),0) -> 0 | ... AV39: =IF(AV$9=$I$54,AV30/($J$57-$J$58),0) -> 0
C40: FCF Including TV | J40: =Assumptions!$G$14 -> USD | S40: =SUM(S38:S39) -> 425584.57 | T40: =SUM(T38:T39) -> 655243.32 | U40: =SUM(U38:U39) -> 658047.97 | V40: =SUM(V38:V39) -> 655016.98 | W40: =SUM(W38:W39) -> 645717.67 | X40: =SUM(X38:X39) -> 629695.87 | Y40: =SUM(Y38:Y39) -> 606475.07 | Z40: =SUM(Z38:Z39) -> 575555.48 | ... AV40: =SUM(AV38:AV39) -> 0
C41: Discount Factor | J41: x | S41: =1/(1+$I$57) -> 0.90981463 | T41: =S41/(1+$I$57) -> 0.82776265 | U41: =T41/(1+$I$57) -> 0.75311057 | V41: =U41/(1+$I$57) -> 0.68519101 | W41: =V41/(1+$I$57) -> 0.6233968 | X41: =W41/(1+$I$57) -> 0.56717553 | Y41: =X41/(1+$I$57) -> 0.51602459 | Z41: =Y41/(1+$I$57) -> 0.46948672 | AA41: =Z41/(1+$I$57) -> 0.42714588 | ... AV41: =AU41/(1+$I$57) -> 0.05869315
C43: Value | D43: Stage I | J43: =Assumptions!$G$14 -> USD | R43: =SUM(S43:AW43) -> 4064979.7 | S43: =S38*S$41 -> 387203.06 | T43: =T38*T$41 -> 542385.95 | U43: =U38*U$41 -> 495582.88 | V43: =V38*V$41 -> 448811.75 | W43: =W38*W$41 -> 402538.33 | X43: =X38*X$41 -> 357148.09 | Y43: =Y38*Y$41 -> 312956.05 | Z43: =Z38*Z$41 -> 270215.65 | ... AV43: =AV38*AV$41 -> 0
C44: Value | D44: Stage II | J44: =Assumptions!$G$14 -> USD | R44: =SUM(S44:AW44) -> 314485.35 | S44: =S39*S$41 -> 0 | T44: =T39*T$41 -> 0 | U44: =U39*U$41 -> 0 | V44: =V39*V$41 -> 0 | W44: =W39*W$41 -> 0 | X44: =X39*X$41 -> 0 | Y44: =Y39*Y$41 -> 0 | Z44: =Z39*Z$41 -> 0 | ... AV44: =AV39*AV$41 -> 0
C45: Total Value | J45: =Assumptions!$G$14 -> USD | R45: =SUM(S45:AV45) -> 4379465.1 | S45: =SUM(S43:S44) -> 387203.06 | T45: =SUM(T43:T44) -> 542385.95 | U45: =SUM(U43:U44) -> 495582.88 | V45: =SUM(V43:V44) -> 448811.75 | W45: =SUM(W43:W44) -> 402538.33 | X45: =SUM(X43:X44) -> 357148.09 | Y45: =SUM(Y43:Y44) -> 312956.05 | Z45: =SUM(Z43:Z44) -> 270215.65 | ... AV45: =SUM(AV43:AV44) -> 0
C47: ="TV "&C7 -> TV Two Stage Value Driver | J47: =Financials!G30 -> USD | R47: =SUM(S45:AV45) -> 4379465.1
C50: Assumptions | N50: ="Comparison: "&C7&" vs. "&'Terminal Value'!C24&" (FCF and ROIC)" -> Comparison: Two Stage Value Driver vs. Gordon Growth (FCF and ROIC)
N51: =C30&" ("&J30&")" -> Free Cash Flow to Firm (USD) | AF51: =C88&" ("&J88&")" -> ROIC Two Stage Value Driver (%)
C52: Stage | I52: Stage I | J52: Stage II
C54: =Assumptions!K91 -> Duration of Competitive Advantage | H54: =Assumptions!L91 -> Years | I54: =Assumptions!M91 -> 15 | J54: =Assumptions!O91 -> NA
C55: =Assumptions!K92 -> Start | H55: =Assumptions!L92 -> Year | I55: =Assumptions!M92 -> 6 | J55: =Assumptions!O92 -> 21
C56: =Assumptions!K93 -> End | H56: =Assumptions!L93 -> Year | I56: =Assumptions!M93 -> 20 | J56: =Assumptions!O93 -> Infinite
C57: =Assumptions!K94 -> Discount Rate | H57: =Assumptions!L94 -> % | I57: =Assumptions!M94 -> 0.099125 | J57: =Assumptions!O94 -> 0.099125
C58: =Assumptions!K97 -> Growth Rate | H58: =Assumptions!L97 -> % | I58: =Assumptions!M97 -> 0.025 | J58: =Assumptions!O97 -> 0.025
C59: =Assumptions!K98 -> Spread to Discount Rate | H59: =Assumptions!L98 -> % | I59: =Assumptions!M98 -> 0.635598 | J59: =Assumptions!O98 -> 0
C60: =Assumptions!K99 -> ROIC | H60: =Assumptions!L99 -> % | I60: =Assumptions!M99 -> 0.734723 | J60: =Assumptions!O99 -> 0.099125
C61: =Assumptions!K100 -> ROIC Curve | H61: =Assumptions!L100 -> % | I61: =Assumptions!M100 -> Exponential Decline
C64: Graph Selector
D66: =C84 -> FCF Forecast Period
D67: =C85 -> FCF Gordon Growth
D68: =C86 -> FCF Two Stage Value Driver
D69: =C87 -> ROIC Gordon Growth
D70: =C88 -> ROIC Two Stage Value Driver
D71: =C89 -> Discount Rate (WACC)
C73: Terminal Value
C75: Value | D75: Stage I | G75: =Assumptions!$G$14 -> USD | H75: =R43 -> 4064979.7
D76: Stage II | G76: =Assumptions!$G$14 -> USD | H76: =R44 -> 314485.35
C78: =C47 -> TV Two Stage Value Driver | G78: =Assumptions!$G$14 -> USD | H78: =R47 -> 4379465.1 | AY78: =SUM(H75:H77)-H78 -> 0
C81: Chart Data
C82: =C8 -> Year | N82: =N8 -> 1 | O82: =O8 -> 2 | P82: =P8 -> 3 | Q82: =Q8 -> 4 | R82: =R8 -> 5 | S82: =S8 -> 6 | T82: =T8 -> 7 | U82: =U8 -> 8 | ... AV82: =AV8 -> 35
C84: FCF Forecast Period | I84: TRUE | J84: =Assumptions!$G$14 -> USD | N84: =IF($I84,N30,NA()) -> 876134.65 | O84: =IF($I84,O30,NA()) -> 931110.6 | P84: =IF($I84,P30,NA()) -> 995341.62 | Q84: =IF($I84,Q30,NA()) -> 745484.18 | R84: =IF($I84,R30,NA()) -> 988105.73
C85: FCF Gordon Growth | I85: TRUE | J85: =Assumptions!$G$14 -> USD | S85: =IF($I85,R30*(1+'Terminal Value'!$H$36),0) -> 1012808.4 | T85: =IF($I85,S30*(1+'Terminal Value'!$H$36),0) -> 436224.18 | U85: =IF($I85,T30*(1+'Terminal Value'!$H$36),0) -> 671624.41 | V85: =IF($I85,U30*(1+'Terminal Value'!$H$36),0) -> 674499.17 | W85: =IF($I85,V30*(1+'Terminal Value'!$H$36),0) -> 671392.41 | X85: =IF($I85,W30*(1+'Terminal Value'!$H$36),0) -> 661860.61 | Y85: =IF($I85,X30*(1+'Terminal Value'!$H$36),0) -> 645438.27 | Z85: =IF($I85,Y30*(1+'Terminal Value'!$H$36),0) -> 621636.95 | ... AV85: =IF($I85,AU30*(1+'Terminal Value'!$H$36),0) -> 139357.2
C86: ="FCF "&$C$7 -> FCF Two Stage Value Driver | I86: TRUE | J86: =Assumptions!$G$14 -> USD | S86: =IF($I86,S30,NA()) -> 425584.57 | T86: =IF($I86,T30,NA()) -> 655243.32 | U86: =IF($I86,U30,NA()) -> 658047.97 | V86: =IF($I86,V30,NA()) -> 655016.98 | W86: =IF($I86,W30,NA()) -> 645717.67 | X86: =IF($I86,X30,NA()) -> 629695.87 | Y86: =IF($I86,Y30,NA()) -> 606475.07 | Z86: =IF($I86,Z30,NA()) -> 575555.48 | ... AV86: =IF($I86,AV30,NA()) -> 139357.2
C87: =C14&" Gordon Growth" -> ROIC Gordon Growth | I87: TRUE | J87: % | S87: =IF($I87,R88,NA()) -> 0.734723 | T87: =IF($I87,S87,NA()) -> 0.734723 | U87: =IF($I87,T87,NA()) -> 0.734723 | V87: =IF($I87,U87,NA()) -> 0.734723 | W87: =IF($I87,V87,NA()) -> 0.734723 | X87: =IF($I87,W87,NA()) -> 0.734723 | Y87: =IF($I87,X87,NA()) -> 0.734723 | Z87: =IF($I87,Y87,NA()) -> 0.734723 | AA87: =IF($I87,Z87,NA()) -> 0.734723 | ... AV87: =IF($I87,AU87,NA()) -> 0.734723
C88: =C15&" "&$C$7 -> ROIC Two Stage Value Driver | I88: TRUE | J88: % | N88: =IF($I88,N15,NA()) -> 0.2876138 | O88: =IF($I88,O15,NA()) -> 0.44169989 | P88: =IF($I88,P15,NA()) -> 0.58709387 | Q88: =IF($I88,Q15,NA()) -> 0.6676804 | R88: =IF($I88,R15,NA()) -> 0.734723 | S88: =IF($I88,S15,NA()) -> 0.73189812 | T88: =IF($I88,T15,NA()) -> 0.72342348 | U88: =IF($I88,U15,NA()) -> 0.70929908 | ... AV88: =IF($I88,AV15,NA()) -> 0.099125
C89: =Assumptions!C60 -> Discount Rate (WACC) | H89: =Assumptions!$G$60 -> 0.099125 | I89: TRUE | J89: % | N89: =IF($I89,$H89,NA()) -> 0.099125 | O89: =IF($I89,$H89,NA()) -> 0.099125 | P89: =IF($I89,$H89,NA()) -> 0.099125 | Q89: =IF($I89,$H89,NA()) -> 0.099125 | R89: =IF($I89,$H89,NA()) -> 0.099125 | S89: =IF($I89,$H89,NA()) -> 0.099125 | T89: =IF($I89,$H89,NA()) -> 0.099125 | U89: =IF($I89,$H89,NA()) -> 0.099125 | ... AV89: =IF($I89,$H89,NA()) -> 0.099125
